Workbook
Name Slicer_Subsidiary: #N/A

Sheet Sheet3
G14: Marzo
A15: Abril | G15: Row Labels | H15: Sum of Amount Remaining
A16: Row Labels | B16: Sum of Amount Remaining | G16: Americas | H16: 1964139.4 | J16: =GETPIVOTDATA("Amount Remaining",$A$16,"Subsidiary","Americas")-H16 -> -835002.12
A17: Americas | B17: 1129137.3 | G17: APAC | H17: 4210.652
A18: APAC | B18: 225886.59 | G18: EMEA | H18: 37757.611
A19: EMEA | B19: 1560344.9 | G19: Sysomos | H19: 313476.89
A20: Grand Total | B20: 2915368.8 | G20: Grand Total | H20: 4792721.2
F28: By Region/YR
F29: Sum of Amount Remaining
F30: 1129137.3

Sheet Sheet4
A12: Row Labels | B12: Sum of Amount Remaining | E12: Row Labels | F12: Sum of Amount Remaining
A13: Americas | B13: 1129137.3 | E13: Americas | F13: 1129137.3
A14: APAC | B14: 225886.59 | E14: APAC | F14: 225886.59
A15: EMEA | B15: 1558558.2 | E15: EMEA | F15: 1558558.2
A16: Grand Total | B16: 2913582.1 | E16: Grand Total | F16: 2913582.1
A20: By Region/YR
A22: SUBSIDIARY | B22: Americas | E22: SUBSIDIARY | F22: APAC | H22: SUBSIDIARY | I22: EMEA
A24: Row Labels | B24: Sum of Amount Remaining | E24: Row Labels | F24: Sum of Amount Remaining | H24: Row Labels | I24: Sum of Amount Remaining
A25: 2022 | B25: 247647.77 | E25: 2022 | F25: 6331.471 | H25: 2022 | I25: 136434.15
A26: 2023 | B26: 161269.48 | E26: 2023 | F26: 118148.64 | H26: 2023 | I26: 320347.94
A27: 2024 | B27: 47448.118 | E27: 2024 | F27: 20152.823 | H27: 2024 | I27: 219682.33
A28: 2025 | B28: 369312.24 | E28: 2025 | F28: 25616.49 | H28: 2025 | I28: 341332.87
A29: 2026 | B29: 303459.69 | E29: 2026 | F29: 55637.166 | H29: 2026 | I29: 541621.09
A30: Grand Total | B30: 1129137.3 | E30: Grand Total | F30: 225886.59 | H30: Grand Total | I30: 1559418.4

Sheet UnappliedPaymentsErnestoResult
A1: Subsidiary (no hierarchy) | B1: Date | C1: MES | D1: AÑO | E1: SUBSIDIARY | F1: Status | G1: Number | H1: Invoice Number | I1: Currency | J1: Amount Base | K1: Amount USD | L1: Amount Remaining | M1: Balance | N1: Customer Name | O1: AR Specialist | P1: Memo
A2: 102 - US | B2: 45736 | C2: =UPPER(TEXT(B2, "[$-en-US]mmmm")) -> MARCH | D2: =YEAR(B2) -> 2025 | E2: =VLOOKUP(A2,Sheet2!A:B,2,0) -> Americas | F2: Deposited | G2: PMT-S151-202999 | I2: USD | J2: -81229.11 | K2: -81229.11 | L2: 81229.11 | M2: -250567.82 | N2: DUMMY CUSTOMER_CASHAPPS 102 - US | P2: ACH CONCENTRATION CREDIT ACH CORP TRADE PAYMENT FROM MICROSOFT MICROSOFT 0004992933 68251185441010
A3: 102 - US | B3: 45922 | C3: =UPPER(TEXT(B3, "[$-en-US]mmmm")) -> SEPTEMBER | D3: =YEAR(B3) -> 2025 | E3: =VLOOKUP(A3,Sheet2!A:B,2,0) -> Americas | F3: Deposited | G3: PMT-S151-211138 | I3: USD | J3: -54445.55 | K3: -54445.55 | L3: 54445.55 | M3: -50095.55 | N3: Microsoft Corporation | P3: ACH CONCENTRATION CREDIT ACH CORP TRADE PAYMENT FROM MICROSOFT MICROSOFT 0005317824 68550845931010
A4: 102 - US | B4: 46071 | C4: =UPPER(TEXT(B4, "[$-en-US]mmmm")) -> FEBRUARY | D4: =YEAR(B4) -> 2026 | E4: =VLOOKUP(A4,Sheet2!A:B,2,0) -> Americas | F4: Deposited | G4: PMT-S151-219775 | I4: USD | J4: -35534 | K4: -35534 | L4: 35534 | M4: -35534 | N4: Brick Media | P4: INCOMING MONEY TRANSFER 53RECD FED JPMORGAN CHASE BANK*ORG:BRICK MEDIA LLC,RO CKY RIVER OH 44116-1815 US,19885 DETRO*OGB:JPMORGAN CHASE BANK,TAMPA,10410 HI GHLAND MANOR DRIVE*BNF:MELTWATER NEWS US INC,REDWOOD CITY CA/US,275 S HO*STFEDSEQ:B1Q8982R000363*TIME:0341*YOUR REF:WTH OF 26/02/18*OUR REF:0490937 10
A5: 102 - US | B5: 45691 | C5: =UPPER(TEXT(B5, "[$-en-US]mmmm")) -> FEBRUARY | D5: =YEAR(B5) -> 2025 | E5: =VLOOKUP(A5,Sheet2!A:B,2,0) -> Americas | F5: Deposited | G5: PMT-S151-200395 | I5: USD | J5: -32613.85 | K5: -32613.85 | L5: 32613.85 | M5: -250567.82 | N5: DUMMY CUSTOMER_CASHAPPS 102 - US | P5: ACH CONCENTRATION CREDIT ACH CORP TRADE PAYMENT FROM MICROSOFT MICROSOFT 0004890122 68550745441010
A6: 102 - US | B6: 44851 | C6: =UPPER(TEXT(B6, "[$-en-US]mmmm")) -> OCTOBER | D6: =YEAR(B6) -> 2022 | E6: =VLOOKUP(A6,Sheet2!A:B,2,0) -> Americas | F6: Deposited | G6: PMT-S151-156272 | I6: USD | J6: -27218.77 | K6: -27218.77 | L6: 27218.77 | M6: -27218.77 | N6: ComplySci | P6: ACH CONCENTRATION CREDIT ACH CASH CONCENTRATION COMPLYSCI-PAYMENT ComplySci Payment 46810
A7: 102 - US | B7: 45856 | C7: =UPPER(TEXT(B7, "[$-en-US]mmmm")) -> JULY | D7: =YEAR(B7) -> 2025 | E7: =VLOOKUP(A7,Sheet2!A:B,2,0) -> Americas | F7: Deposited | G7: PMT-S151-208003 | I7: USD | J7: -25699.72 | K7: -25699.72 | L7: 25699.72 | M7: -250567.82 | N7: DUMMY CUSTOMER_CASHAPPS 102 - US | P7: ACH CONCENTRATION CREDIT ACH CASH CONCENTRATION ENVIOLOL-PAYMENTS ENVIOLOL PAYMENTS 0000010593
A8: 102 - US | B8: 45838 | C8: =UPPER(TEXT(B8, "[$-en-US]mmmm")) -> JUNE | D8: =YEAR(B8) -> 2025 | E8: =VLOOKUP(A8,Sheet2!A:B,2,0) -> Americas | F8: Deposited | G8: PMT-S151-207105 | I8: USD | J8: -24128 | K8: -24128 | L8: 24128 | M8: -250567.82 | N8: DUMMY CUSTOMER_CASHAPPS 102 - US | P8: ACH CONCENTRATION CREDIT ACH CORP TRADE PAYMENT FROM MICROSOFT MICROSOFT 0005162418 68500854311010
A9: 102 - US | B9: 46118 | C9: =UPPER(TEXT(B9, "[$-en-US]mmmm")) -> APRIL | D9: =YEAR(B9) -> 2026 | E9: =VLOOKUP(A9,Sheet2!A:B,2,0) -> Americas | F9: Deposited | G9: PMT-S151-222326 | I9: USD | J9: -20913.77 | K9: -20913.77 | L9: 20913.77 | M9: -20913.77 | N9: Camp Chef | P9: ACH CONCENTRATION CREDIT ACH CASH CONCENTRATION BUSHNELL OPER-PAYMENT BUSHNELL PAYMENT 2021416
A10: 102 - US | B10: 46127 | C10: =UPPER(TEXT(B10, "[$-en-US]mmmm")) -> APRIL | D10: =YEAR(B10) -> 2026 | E10: =VLOOKUP(A10,Sheet2!A:B,2,0) -> Americas | F10: Deposited | G10: PMT-S151-222780 | I10: USD | J10: -20698 | K10: -20698 | L10: 20698 | M10: -20698 | N10: Culloton + Bauer Luce | P10: ACH CONCENTRATION CREDIT ACH CASH CONCENTRATION CULLOTON STRATEG-ACH PAYMEN Culloton ACH Paymen 95267
A11: 102 - US | B11: 45889 | C11: =UPPER(TEXT(B11, "[$-en-US]mmmm")) -> AUGUST | D11: =YEAR(B11) -> 2025 | E11: =VLOOKUP(A11,Sheet2!A:B,2,0) -> Americas | F11: Deposited | G11: PMT-S151-209700 | I11: USD | J11: -20000 | K11: -20000 | L11: 20000 | M11: -50095.55 | N11: Microsoft Corporation | P11: ACH CONCENTRATION CREDIT ACH CORP TRADE PAYMENT FROM MICROSOFT MICROSOFT 0005263117 68151120631010
A12: 102 - US | B12: 46108 | C12: =UPPER(TEXT(B12, "[$-en-US]mmmm")) -> MARCH | D12: =YEAR(B12) -> 2026 | E12: =VLOOKUP(A12,Sheet2!A:B,2,0) -> Americas | F12: Deposited | G12: PMT-S151-221843 | H12: PMT-S151-221843 | I12: USD | J12: -39600 | K12: -39600 | L12: 19800 | M12: -19800 | N12: Blue Learning | P12: ACH CONCENTRATION CREDIT ACH CASH CONCENTRATION BLUE LEARNING OP-CORP PAY BLUE LEAR CORP PAY 10957
A13: 102 - US | B13: 46139 | C13: =UPPER(TEXT(B13, "[$-en-US]mmmm")) -> APRIL | D13: =YEAR(B13) -> 2026 | E13: =VLOOKUP(A13,Sheet2!A:B,2,0) -> Americas | F13: Deposited | G13: PMT-S151-223322 | I13: USD | J13: -19350 | K13: -19350 | L13: 19350 | M13: -19350 | N13: Gaudenzia, Inc
A14: 102 - US | B14: 45049 | C14: =UPPER(TEXT(B14, "[$-en-US]mmmm")) -> MAY | D14: =YEAR(B14) -> 2023 | E14: =VLOOKUP(A14,Sheet2!A:B,2,0) -> Americas | F14: Deposited | G14: PMT-S151-167535 | I14: USD | J14: -18060 | K14: -18060 | L14: 18060 | M14: -18060 | N14: Sun Valley Resort | P14: CHECK
A15: 102 - US | B15: 44652 | C15: =UPPER(TEXT(B15, "[$-en-US]mmmm")) -> APRIL | D15: =YEAR(B15) -> 2022 | E15: =VLOOKUP(A15,Sheet2!A:B,2,0) -> Americas | F15: Deposited | G15: PMT-S151-145279 | I15: USD | J15: -17850.4 | K15: -17850.4 | L15: 17850.4 | M15: -17850.4 | N15: Netchoice | P15: FOREIGN REMITTANCE CREDIT 33RECD CHIP WELLS FARGO BANK,SAN FRANCISCO,CA*O RG:NETCHOICE,US 20005-3417,WASHINGTON DC,1401 K S*BNF:MELTWATER NEW S US INC,SAN FRANCISCO CA/US,STE 100*OBI:INVOICE S151 535230*STCHIPSEQ :0499781*TIME:1511*YOUR REF:643*OUR REF:091587415
A16: 102 - US | B16: 46132 | C16: =UPPER(TEXT(B16, "[$-en-US]mmmm")) -> APRIL | D16: =YEAR(B16) -> 2026 | E16: =VLOOKUP(A16,Sheet2!A:B,2,0) -> Americas | F16: Deposited | G16: PMT-S151-223019 | I16: USD | J16: -17200 | K16: -17200 | L16: 17200 | M16: 0 | N16: Gordon State College | P16: ACH CONCENTRATION CREDIT ACH CORP TRADE PAYMENT FROM Gordon State Col Gordon St CTX 0000039074
A17: 102 - US | B17: 44907 | C17: =UPPER(TEXT(B17, "[$-en-US]mmmm")) -> DECEMBER | D17: =YEAR(B17) -> 2022 | E17: =VLOOKUP(A17,Sheet2!A:B,2,0) -> Americas | F17: Deposited | G17: PMT-S151-159463 | I17: USD | J17: -16500 | K17: -16500 | L17: 16500 | M17: 3500 | N17: Bayhealth Medical Center | P17: CHECK
A18: 102 - US | B18: 46143 | C18: =UPPER(TEXT(B18, "[$-en-US]mmmm")) -> MAY | D18: =YEAR(B18) -> 2026 | E18: =VLOOKUP(A18,Sheet2!A:B,2,0) -> Americas | F18: Deposited | G18: PMT-S151-223708 | I18: USD | J18: -16483 | K18: -16483 | L18: 16483 | M18: -16483 | N18: Washington Times Global Media Group | O18: Jordan Irvine | P18: ACH CREDIT ACH DEPOSIT FROM WASHINGTON TIMES-CREDITS WASHINGTO CREDITS TWT-22920
A19: 102 - US | B19: 46056 | C19: =UPPER(TEXT(B19, "[$-en-US]mmmm")) -> FEBRUARY | D19: =YEAR(B19) -> 2026 | E19: =VLOOKUP(A19,Sheet2!A:B,2,0) -> Americas | F19: Deposited | G19: PMT-S151-218617 | H19: IN-S151-589402 | I19: USD | J19: -16000 | K19: -16000 | L19: 15999.84 | M19: -15999.84 | N19: West Palm Beach Downtown Development Authority | O19: Jose Castellanos
A20: 102 - US | B20: 44680 | C20: =UPPER(TEXT(B20, "[$-en-US]mmmm")) -> APRIL | D20: =YEAR(B20) -> 2022 | E20: =VLOOKUP(A20,Sheet2!A:B,2,0) -> Americas | F20: Deposited | G20: PMT-S151-146709 | I20: USD | J20: -15750 | K20: -15750 | L20: 15750 | M20: -15750 | N20: Kean University | O20: Kristin Walsh
A21: 102 - US | B21: 46139 | C21: =UPPER(TEXT(B21, "[$-en-US]mmmm")) -> APRIL | D21: =YEAR(B21) -> 2026 | E21: =VLOOKUP(A21,Sheet2!A:B,2,0) -> Americas | F21: Deposited | G21: PMT-S151-223397 | I21: USD | J21: -15000 | K21: -15000 | L21: 15000 | M21: -15000 | N21: Nautilus Solar Energy, LLC | P21: ACH CONCENTRATION CREDIT ACH CASH CONCENTRATION NAUTILUS SOLAR E-ACH PMT NAUTILUS ACH Pmt 11216430243
A22: 102 - US | B22: 45996 | C22: =UPPER(TEXT(B22, "[$-en-US]mmmm")) -> DECEMBER | D22: =YEAR(B22) -> 2025 | E22: =VLOOKUP(A22,Sheet2!A:B,2,0) -> Americas | F22: Deposited | G22: PMT-S151-215069 | I22: USD | J22: -14145.99 | K22: -14145.99 | L22: 14145.99 | M22: 154725.09 | N22: Amazon.com Services LLC | P22: ACH CONCENTRATION CREDIT ACH CASH CONCENTRATION AMAZON.COM-EDI PYMNTS AMAZON.CO EDI PYMNTS DAS4VG6U2FWEEBQ
A23: 102 - US | B23: 45614 | C23: =UPPER(TEXT(B23, "[$-en-US]mmmm")) -> NOVEMBER | D23: =YEAR(B23) -> 2024 | E23: =VLOOKUP(A23,Sheet2!A:B,2,0) -> Americas | F23: Deposited | G23: PMT-S151-196679 | I23: USD | J23: -13975 | K23: -13975 | L23: 13975 | M23: -250567.82 | N23: DUMMY CUSTOMER_CASHAPPS 102 - US | P23: FOREIGN REMITTANCE CREDIT 33RECD CHIP JPMORGAN CHASE BANK*ORG:BYTECHIP LLC,UNITED STATES,US ,8 THE GREEN, SUITE B, DOVE*OGB:RD WALLET TECHNOLOGIES LIMITED,CAUSEWAY BAY,535 JAFFE RO*BNF:MELTWATER NEWS US INC,REDWOOD CITY CA/US,STE 165*OBI:202411080803*STCHIPSEQ:00209649*TIME:0248 *YOUR REF:1513OT8581513*OUR REF:323200531
A24: 102 - US | B24: 44694 | C24: =UPPER(TEXT(B24, "[$-en-US]mmmm")) -> MAY | D24: =YEAR(B24) -> 2022 | E24: =VLOOKUP(A24,Sheet2!A:B,2,0) -> Americas | F24: Deposited | G24: PMT-S151-147498 | I24: USD | J24: -13650 | K24: -13650 | L24: 13650 | M24: -13650 | N24: Florida Dept. of Agriculture and Consumer Services | O24: Jordan Irvine | P24: CHECK
A25: 102 - US | B25: 45910 | C25: =UPPER(TEXT(B25, "[$-en-US]mmmm")) -> SEPTEMBER | D25: =YEAR(B25) -> 2025 | E25: =VLOOKUP(A25,Sheet2!A:B,2,0) -> Americas | F25: Deposited | G25: PMT-S151-210583 | I25: USD | J25: -13564.62 | K25: -13564.62 | L25: 13564.62 | M25: -13564.62 | N25: Cubic Corporation | O25: Jose Castellanos | P25: Customer refund ACH CONCENTRATION CREDIT ACH CASH CONCENTRATION CUBIC CORPORATIO-EDI/ACH Cubic Cor EDI/ACH 10152000245 624
A26: 102 - US | B26: 45167 | C26: =UPPER(TEXT(B26, "[$-en-US]mmmm")) -> AUGUST | D26: =YEAR(B26) -> 2023 | E26: =VLOOKUP(A26,Sheet2!A:B,2,0) -> Americas | F26: Deposited | G26: PMT-S151-173898 | I26: USD | J26: -13500 | K26: -13500 | L26: 13500 | M26: -13500 | N26: Versant Health | P26: CHECK
A27: 102 - US | B27: 45085 | C27: =UPPER(TEXT(B27, "[$-en-US]mmmm")) -> JUNE | D27: =YEAR(B27) -> 2023 | E27: =VLOOKUP(A27,Sheet2!A:B,2,0) -> Americas | F27: Deposited | G27: PMT-S151-169476 | I27: USD | J27: -12980 | K27: -12980 | L27: 12980 | M27: -250567.82 | N27: DUMMY CUSTOMER_CASHAPPS 102 - US | P27: ACH CONCENTRATION CREDIT ACH CASH CONCENTRATION DALLAS FOUNDATIO-CORP PAY DALLAS FO CORP PAY 1504
A28: 102 - US | B28: 44830 | C28: =UPPER(TEXT(B28, "[$-en-US]mmmm")) -> SEPTEMBER | D28: =YEAR(B28) -> 2022 | E28: =VLOOKUP(A28,Sheet2!A:B,2,0) -> Americas | F28: Deposited | G28: PMT-S151-154814 | I28: USD | J28: -11550 | K28: -11550 | L28: 11550 | M28: -11550 | N28: AmeriCU Credit Union | P28: CHECK
A29: 102 - US | B29: 45174 | C29: =UPPER(TEXT(B29, "[$-en-US]mmmm")) -> SEPTEMBER | D29: =YEAR(B29) -> 2023 | E29: =VLOOKUP(A29,Sheet2!A:B,2,0) -> Americas | F29: Deposited | G29: PMT-S151-174242 | H29: IN-S151-555435 | I29: USD | J29: -22698.13 | K29: -22698.13 | L29: 11349.07 | M29: -11349.07 | N29: Drive Agency, LLC | O29: Yangzom Vitali-116 | P29: ACH CREDIT ACH DEPOSIT FROM GREENBERG QUINLA-ACH PAYMNT INV IN-S151-548883
A30: 102 - US | B30: 46136 | C30: =UPPER(TEXT(B30, "[$-en-US]mmmm")) -> APRIL | D30: =YEAR(B30) -> 2026 | E30: =VLOOKUP(A30,Sheet2!A:B,2,0) -> Americas | F30: Deposited | G30: PMT-S151-223327 | I30: USD | J30: -9900 | K30: -9900 | L30: 9900 | M30: -250567.82 | N30: DUMMY CUSTOMER_CASHAPPS 102 - US | P30: ACH CONCENTRATION CREDIT ACH CASH CONCENTRATION COMMISSION L'UNI-PAYMENT COMMISSIO PAYMENT KQ3LUSEQGD69
A31: 102 - US | B31: 45114 | C31: =UPPER(TEXT(B31, "[$-en-US]mmmm")) -> JULY | D31: =YEAR(B31) -> 2023 | E31: =VLOOKUP(A31,Sheet2!A:B,2,0) -> Americas | F31: Deposited | G31: PMT-S151-171074 | I31: USD | J31: -9695 | K31: -9695 | L31: 9695 | M31: -10420 | N31: Amarin Pharma, Inc. | O31: Sarah Shoemaker-MW | P31: FOREIGN REMITTANCE CREDIT 33RECD CHIP JPMORGAN CHASE BANK*ORG:AMARIN SWITZERLAND GMBH,CH/ZUG 6300,BAARERSTRASSE 75*OGB:JPMORGAN CHASE BANK,N.A.,ZUERICH,DREI KOENIGSTRASSE 21*BNF:MELTWATER NEWS US INC,REDWOOD CITY CA/US,STE 165 *OBI:/ROC/714*STCHIPSEQ:0157130*TIME:0207*YOUR REF:SWF OF 23/07/07*OUR REF:18 8409072
A32: 102 - US | B32: 45684 | C32: =UPPER(TEXT(B32, "[$-en-US]mmmm")) -> JANUARY | D32: =YEAR(B32) -> 2025 | E32: =VLOOKUP(A32,Sheet2!A:B,2,0) -> Americas | F32: Deposited | G32: PMT-S151-199815 | I32: USD | J32: -9680 | K32: -9680 | L32: 9680 | M32: -9680 | N32: Zonda Home | P32: ACH CONCENTRATION CREDIT ACH CASH CONCENTRATION METROSTUDY INC-AB-TFBANIP METROSTUD AB-TFBANIP 4090116
A33: 102 - US | B33: 46031 | C33: =UPPER(TEXT(B33, "[$-en-US]mmmm")) -> JANUARY | D33: =YEAR(B33) -> 2026 | E33: =VLOOKUP(A33,Sheet2!A:B,2,0) -> Americas | F33: Deposited | G33: PMT-S151-217064 | I33: USD | J33: -9600 | K33: -9600 | L33: 9600 | M33: -9600 | N33: Hunstville Botanical Garden | P33: ACH CONCENTRATION CREDIT ACH CASH CONCENTRATION HSV BG 517-ACH PAYMEN HSV BG ACH Paymen 32465974
A34: 102 - US | B34: 44852 | C34: =UPPER(TEXT(B34, "[$-en-US]mmmm")) -> OCTOBER | D34: =YEAR(B34) -> 2022 | E34: =VLOOKUP(A34,Sheet2!A:B,2,0) -> Americas | F34: Deposited | G34: PMT-S151-156313 | H34: IN-S151-546649 | I34: USD | J34: -14000 | K34: -14000 | L34: 9333.33 | M34: -9333.33 | N34: Management & Training Corporation (Job Corps) | O34: Jose Castellanos-103 | P34: renewal 12/7/22-12/6/25
A35: 102 - US | B35: 44736 | C35: =UPPER(TEXT(B35, "[$-en-US]mmmm")) -> JUNE | D35: =YEAR(B35) -> 2022 | E35: =VLOOKUP(A35,Sheet2!A:B,2,0) -> Americas | F35: Deposited | G35: PMT-S151-149470 | I35: USD | J35: -8250 | K35: -8250 | L35: 8250 | M35: -8250 | N35: Avendra | P35: CHECK
A36: 102 - US | B36: 44748 | C36: =UPPER(TEXT(B36, "[$-en-US]mmmm")) -> JULY | D36: =YEAR(B36) -> 2022 | E36: =VLOOKUP(A36,Sheet2!A:B,2,0) -> Americas | F36: Deposited | G36: PMT-S151-150211 | I36: USD | J36: -8250 | K36: -8250 | L36: 8250 | M36: -250567.82 | N36: DUMMY CUSTOMER_CASHAPPS 102 - US | P36: ACH CONCENTRATION CREDIT ACH CASH CONCENTRATION INDIANA UNV-BATCH INDIANA U BATCH 504301824
A37: 102 - US | B37: 44956 | C37: =UPPER(TEXT(B37, "[$-en-US]mmmm")) -> JANUARY | D37: =YEAR(B37) -> 2023 | E37: =VLOOKUP(A37,Sheet2!A:B,2,0) -> Americas | F37: Deposited | G37: PMT-S151-162604 | H37: IN-S151-549189 | I37: USD | J37: -15665.62 | K37: -15665.62 | L37: 8165.62 | M37: -8165.62 | N37: Comic Relief, Inc | P37: ACH CONCENTRATION CREDIT ACH CASH CONCENTRATION COMIC RELIEF8654-PAYMENTS COMIC REL PAYMENTS Meltwater N ews
A38: 102 - US | B38: 45856 | C38: =UPPER(TEXT(B38, "[$-en-US]mmmm")) -> JULY | D38: =YEAR(B38) -> 2025 | E38: =VLOOKUP(A38,Sheet2!A:B,2,0) -> Americas | F38: Deposited | G38: PMT-S151-208027 | I38: USD | J38: -7720.17 | K38: -7720.17 | L38: 7720.17 | M38: -250567.82 | N38: DUMMY CUSTOMER_CASHAPPS 102 - US | P38: ACH CONCENTRATION CREDIT ACH CASH CONCENTRATION ENVIOLOL-PAYMENTS ENVIOLOL PAYMENTS 0000010634
A39: 102 - US | B39: 45881 | C39: =UPPER(TEXT(B39, "[$-en-US]mmmm")) -> AUGUST | D39: =YEAR(B39) -> 2025 | E39: =VLOOKUP(A39,Sheet2!A:B,2,0) -> Americas | F39: Deposited | G39: PMT-S151-209317 | I39: USD | J39: -7652 | K39: -7652 | L39: 7652 | M39: -7652 | N39: Fort Worth Symphony Orchestra
A40: 102 - US | B40: 46126 | C40: =UPPER(TEXT(B40, "[$-en-US]mmmm")) -> APRIL | D40: =YEAR(B40) -> 2026 | E40: =VLOOKUP(A40,Sheet2!A:B,2,0) -> Americas | F40: Deposited | G40: PMT-S151-222677 | I40: USD | J40: -7500 | K40: -7500 | L40: 7500 | M40: -250567.82 | N40: DUMMY CUSTOMER_CASHAPPS 102 - US
A41: 102 - US | B41: 45205 | C41: =UPPER(TEXT(B41, "[$-en-US]mmmm")) -> OCTOBER | D41: =YEAR(B41) -> 2023 | E41: =VLOOKUP(A41,Sheet2!A:B,2,0) -> Americas | F41: Deposited | G41: PMT-S151-175978 | I41: USD | J41: -7350 | K41: -7350 | L41: 7350 | M41: -7350 | N41: American Magic | P41: ACH CONCENTRATION CREDIT ACH CASH CONCENTRATION BMQR-SPT ACH BMQR SPT ACH Meltwater
A42: 102 - US | B42: 45688 | C42: =UPPER(TEXT(B42, "[$-en-US]mmmm")) -> JANUARY | D42: =YEAR(B42) -> 2025 | E42: =VLOOKUP(A42,Sheet2!A:B,2,0) -> Americas | F42: Deposited | G42: PMT-S151-200236 | I42: USD | J42: -7150 | K42: -7150 | L42: 7150 | M42: -250567.82 | N42: DUMMY CUSTOMER_CASHAPPS 102 - US | P42: ACH CONCENTRATION CREDIT ACH CORP TRADE PAYMENT FROM THE CITY OF NEW THE CITY Payments 202501296563717
A43: 102 - US | B43: 44838 | C43: =UPPER(TEXT(B43, "[$-en-US]mmmm")) -> OCTOBER | D43: =YEAR(B43) -> 2022 | E43: =VLOOKUP(A43,Sheet2!A:B,2,0) -> Americas | F43: Deposited | G43: PMT-S151-155504 | I43: USD | J43: -7000 | K43: -7000 | L43: 7000 | M43: -7000 | N43: Girl Scouts of Northeast Texas | P43: ACH CONCENTRATION CREDIT ACH CASH CONCENTRATION GIRL SCOUTS OF N-PAYMENTS GIRL SCOU PAYMENTS MELTWATER
A44: 102 - US | B44: 44897 | C44: =UPPER(TEXT(B44, "[$-en-US]mmmm")) -> DECEMBER | D44: =YEAR(B44) -> 2022 | E44: =VLOOKUP(A44,Sheet2!A:B,2,0) -> Americas | F44: Deposited | G44: PMT-S151-159053 | H44: IN-S151-547293 | I44: USD | J44: -20000 | K44: -20000 | L44: 7000 | M44: -7000 | N44: SSR Mining, Inc | P44: ACH CREDIT ACH DEPOSIT FROM SSR MINING INC.-AP PAYMENT SSR MININ AP PAYMENT NOTPROVIDED
A45: 102 - US | B45: 45138 | C45: =UPPER(TEXT(B45, "[$-en-US]mmmm")) -> JULY | D45: =YEAR(B45) -> 2023 | E45: =VLOOKUP(A45,Sheet2!A:B,2,0) -> Americas | F45: Deposited | G45: PMT-S151-172289 | H45: IN-S151-568917 | I45: USD | J45: -7750 | K45: -7750 | L45: 6975 | M45: -6975 | N45: Johnston County Schools | O45: Stephanie Thore | P45: CHECK
A46: 102 - US | B46: 45128 | C46: =UPPER(TEXT(B46, "[$-en-US]mmmm")) -> JULY | D46: =YEAR(B46) -> 2023 | E46: =VLOOKUP(A46,Sheet2!A:B,2,0) -> Americas | F46: Deposited | G46: PMT-S151-171846 | I46: USD | J46: -6929 | K46: -6929 | L46: 6929 | M46: -6929 | N46: Season Health | P46: ACH CONCENTRATION CREDIT ACH CASH CONCENTRATION SURELY HEALTH,I-TRANSFER
A47: 102 - US | B47: 46013 | C47: =UPPER(TEXT(B47, "[$-en-US]mmmm")) -> DECEMBER | D47: =YEAR(B47) -> 2025 | E47: =VLOOKUP(A47,Sheet2!A:B,2,0) -> Americas | F47: Deposited | G47: PMT-S151-216041 | H47: PMT-S151-216041 | I47: USD | J47: -6655 | K47: -6655 | L47: 6655 | M47: -6655 | N47: The Commit Partnership | P47: ACH CONCENTRATION CREDIT ACH CASH CONCENTRATION COMMIT2DALLAS-INS1515900
A48: 102 - US | B48: 44924 | C48: =UPPER(TEXT(B48, "[$-en-US]mmmm")) -> DECEMBER | D48: =YEAR(B48) -> 2022 | E48: =VLOOKUP(A48,Sheet2!A:B,2,0) -> Americas | F48: Deposited | G48: PMT-S151-160605 | I48: USD | J48: -6325 | K48: -6325 | L48: 6325 | M48: -6325 | N48: Gulfshore Playhouse | P48: CHECK
A49: 102 - US | B49: 46136 | C49: =UPPER(TEXT(B49, "[$-en-US]mmmm")) -> APRIL | D49: =YEAR(B49) -> 2026 | E49: =VLOOKUP(A49,Sheet2!A:B,2,0) -> Americas | F49: Deposited | G49: PMT-S151-223212 | I49: USD | J49: -6200 | K49: -6200 | L49: 6200 | M49: -6200 | N49: Honolulu Marathon Association | O49: Stephanie Thore
A50: 102 - US | B50: 46146 | C50: =UPPER(TEXT(B50, "[$-en-US]mmmm")) -> MAY | D50: =YEAR(B50) -> 2026 | E50: =VLOOKUP(A50,Sheet2!A:B,2,0) -> Americas | F50: Deposited | G50: PMT-S151-223744 | I50: USD | J50: -5625 | K50: -5625 | L50: 5625 | M50: -5625 | N50: Omaha Supernovas
A51: 102 - US | B51: 44678 | C51: =UPPER(TEXT(B51, "[$-en-US]mmmm")) -> APRIL | D51: =YEAR(B51) -> 2022 | E51: =VLOOKUP(A51,Sheet2!A:B,2,0) -> Americas | F51: Deposited | G51: PMT-S151-146660 | I51: USD | J51: -5505 | K51: -5505 | L51: 5505 | M51: -5505 | N51: Pacvue | P51: ACH CONCENTRATION CREDIT ACH CASH CONCENTRATION PACVUE CORPORATI-ACH PMT PACVUE CO ACH Pmt 5332490959
A52: 102 - US | B52: 45041 | C52: =UPPER(TEXT(B52, "[$-en-US]mmmm")) -> APRIL | D52: =YEAR(B52) -> 2023 | E52: =VLOOKUP(A52,Sheet2!A:B,2,0) -> Americas | F52: Deposited | G52: PMT-S151-167020 | I52: USD | J52: -5500 | K52: -5500 | L52: 5500 | M52: -5500 | N52: Birmingham Public Schools | P52: CHECK
A53: 102 - US | B53: 45154 | C53: =UPPER(TEXT(B53, "[$-en-US]mmmm")) -> AUGUST | D53: =YEAR(B53) -> 2023 | E53: =VLOOKUP(A53,Sheet2!A:B,2,0) -> Americas | F53: Deposited | G53: PMT-S151-173335 | I53: USD | J53: -5500 | K53: -5500 | L53: 5500 | M53: -5500 | N53: Brain Technologies, Inc. | P53: ACH CONCENTRATION CREDIT ACH CASH CONCENTRATION BRAIN TECHNOLOGI-BILL.COM Brain Tec Bill.com 016GNOXUE2QY ILR
A54: 102 - US | B54: 45952 | C54: =UPPER(TEXT(B54, "[$-en-US]mmmm")) -> OCTOBER | D54: =YEAR(B54) -> 2025 | E54: =VLOOKUP(A54,Sheet2!A:B,2,0) -> Americas | F54: Deposited | G54: PMT-S151-212527 | I54: USD | J54: -5500 | K54: -5500 | L54: 5500 | M54: -5500 | N54: Vladimir Jones
A55: 102 - US | B55: 44930 | C55: =UPPER(TEXT(B55, "[$-en-US]mmmm")) -> JANUARY | D55: =YEAR(B55) -> 2023 | E55: =VLOOKUP(A55,Sheet2!A:B,2,0) -> Americas | F55: Deposited | G55: PMT-S151-160930 | I55: USD | J55: -5457 | K55: -5457 | L55: 5457 | M55: -5457 | N55: Calvin Klein | O55: Jason Welch | P55: INCOMING MONEY TRANSFER 53RECD FED BANK OF AMERICA N.A.*ORG:1/PVH EUROPE B .V.,3/NL/AMSTERDAM 1054ES,2/STADHOUDERSKAD*OGB:BANK OF AMERICA NA LONDON,LOND ON,BANK OF AMERICA MERRILL*BNF:MELTWATER NEWS US INC,SAN FRANCISCO CA/ US,STE 100*OBI:IN-S151-531453C PVHE CALVIN KL EIN EUROPE BV /RFB/221019200010 1556*STFEDSEQ:B1Q8982R002942*TIME:1618*YOUR REF:2210192000101556*OUR REF:0045 77450
A56: 102 - US | B56: 45342 | C56: =UPPER(TEXT(B56, "[$-en-US]mmmm")) -> FEBRUARY | D56: =YEAR(B56) -> 2024 | E56: =VLOOKUP(A56,Sheet2!A:B,2,0) -> Americas | F56: Deposited | G56: PMT-S151-183645 | I56: USD | J56: -5400 | K56: -5400 | L56: 5400 | M56: -5400 | N56: Mextenis, S.A. de C.V | O56: Maria Papadopoulos | P56: INCOMING MONEY TRANSFER 53RECD FED BANK OF NEW YORK*ORG:MEX TENIS S.A. DE C.V.,MX 23/10/1992,BOSQUES DE LAS LOMA*OGB:INTERCAM BANCO SA INSTITUCION DE B A,CIUDAD DE MEXICO,COL*BNF:MELTWATER NEWS US INC,REDWOOD CITY CA/US,S TE 165*OBI:PAY LICENCIAMELTWATERPAQ PAGO DE SE RVIC BOF MEX TENIS S.A. DE C.V .*STFEDSEQ:B1Q8981R004078*TIME:1315*YOUR REF NONREF*OUR REF:051500808
A57: 102 - US | B57: 45763 | C57: =UPPER(TEXT(B57, "[$-en-US]mmmm")) -> APRIL | D57: =YEAR(B57) -> 2025 | E57: =VLOOKUP(A57,Sheet2!A:B,2,0) -> Americas | F57: Deposited | G57: PMT-S151-204303 | I57: USD | J57: -5375 | K57: -5375 | L57: 5375 | M57: -5375 | N57: Bath & Body Works Direct, Inc. | P57: ACH CONCENTRATION CREDIT ACH CASH CONCENTRATION L BRAND 1332-EDI PAYMNT L BRAND 1 EDI PAYMNT 2003275583
A58: 102 - US | B58: 45195 | C58: =UPPER(TEXT(B58, "[$-en-US]mmmm")) -> SEPTEMBER | D58: =YEAR(B58) -> 2023 | E58: =VLOOKUP(A58,Sheet2!A:B,2,0) -> Americas | F58: Deposited | G58: PMT-S151-175385 | H58: IN-S151-559205 | I58: USD | J58: -9717.12 | K58: -9717.12 | L58: 5254.62 | M58: -5254.62 | N58: CultureWorks Inc | P58: ACH CONCENTRATION CREDIT ACH CASH CONCENTRATION CULTUREWORKS,IN-BILL.COM CultureWo Bill.com 025BRMYDKVMZ 65U
A59: 102 - US | B59: 45828 | C59: =UPPER(TEXT(B59, "[$-en-US]mmmm")) -> JUNE | D59: =YEAR(B59) -> 2025 | E59: =VLOOKUP(A59,Sheet2!A:B,2,0) -> Americas | F59: Deposited | G59: PMT-S151-206730 | H59: IN-S151-583041 | I59: USD | J59: -55150 | K59: -55150 | L59: 5150 | M59: -50095.55 | N59: Microsoft Corporation | P59: ACH CONCENTRATION CREDIT ACH CASH CONCENTRATION 200-ACTIVISION P-6531011921 200-ACTIV 6531011921 6531011921
A60: 102 - US | B60: 45957 | C60: =UPPER(TEXT(B60, "[$-en-US]mmmm")) -> OCTOBER | D60: =YEAR(B60) -> 2025 | E60: =VLOOKUP(A60,Sheet2!A:B,2,0) -> Americas | F60: Deposited | G60: PMT-S151-212754 | I60: USD | J60: -5000 | K60: -5000 | L60: 5000 | M60: -5000 | N60: McDaniels Marketing
A61: 102 - US | B61: 45980 | C61: =UPPER(TEXT(B61, "[$-en-US]mmmm")) -> NOVEMBER | D61: =YEAR(B61) -> 2025 | E61: =VLOOKUP(A61,Sheet2!A:B,2,0) -> Americas | F61: Deposited | G61: PMT-S151-214232 | I61: USD | J61: -5000 | K61: -5000 | L61: 5000 | M61: -5000 | N61: Mendaera, Inc
A62: 102 - US | B62: 44673 | C62: =UPPER(TEXT(B62, "[$-en-US]mmmm")) -> APRIL | D62: =YEAR(B62) -> 2022 | E62: =VLOOKUP(A62,Sheet2!A:B,2,0) -> Americas | F62: Deposited | G62: PMT-S151-146301 | I62: USD | J62: -4800 | K62: -4800 | L62: 4800 | M62: -4800 | N62: WeGo Public Transit | P62: CHECK
A63: 102 - US | B63: 46135 | C63: =UPPER(TEXT(B63, "[$-en-US]mmmm")) -> APRIL | D63: =YEAR(B63) -> 2026 | E63: =VLOOKUP(A63,Sheet2!A:B,2,0) -> Americas | F63: Deposited | G63: PMT-S151-223214 | I63: USD | J63: -4265.16 | K63: -4265.16 | L63: 4265.16 | M63: -4265.16 | N63: TFI Family Services, Inc. | P63: ACH CONCENTRATION CREDIT ACH CASH CONCENTRATION TFI FAMILY SERVI-ACH PAYMEN TFI Famil ACH Paymen V000000551
A64: 102 - US | B64: 44652 | C64: =UPPER(TEXT(B64, "[$-en-US]mmmm")) -> APRIL | D64: =YEAR(B64) -> 2022 | E64: =VLOOKUP(A64,Sheet2!A:B,2,0) -> Americas | F64: Deposited | G64: PMT-S151-145257 | I64: USD | J64: -4225 | K64: -4225 | L64: 4225 | M64: -4225 | N64: SVB Leerink | P64: ACH CONCENTRATION CREDIT ACH CASH CONCENTRATION LEERINK PRTNRS-TRADE PAY LEERINK P TRADE PAY MELTWATER
A65: 102 - US | B65: 45834 | C65: =UPPER(TEXT(B65, "[$-en-US]mmmm")) -> JUNE | D65: =YEAR(B65) -> 2025 | E65: =VLOOKUP(A65,Sheet2!A:B,2,0) -> Americas | F65: Deposited | G65: PMT-S151-206955 | I65: USD | J65: -4087.75 | K65: -4087.75 | L65: 4087.75 | M65: -4087.75 | N65: FOULGER-PRATT | P65: ACH CONCENTRATION CREDIT ACH CASH CONCENTRATION FOULGERPRATT PMD-PAYMENT FOULGERPR PAYMENT 5543440
A66: 102 - US | B66: 46143 | C66: =UPPER(TEXT(B66, "[$-en-US]mmmm")) -> MAY | D66: =YEAR(B66) -> 2026 | E66: =VLOOKUP(A66,Sheet2!A:B,2,0) -> Americas | F66: Deposited | G66: PMT-S151-223676 | I66: USD | J66: -4026 | K66: -4026 | L66: 4026 | M66: 0 | N66: Philander Smith University | O66: Stephanie Thore
A67: 102 - US | B67: 45457 | C67: =UPPER(TEXT(B67, "[$-en-US]mmmm")) -> JUNE | D67: =YEAR(B67) -> 2024 | E67: =VLOOKUP(A67,Sheet2!A:B,2,0) -> Americas | F67: Deposited | G67: PMT-S151-189268 | H67: IN-S151-564791 | I67: USD | J67: -7983 | K67: -7983 | L67: 3991.5 | M67: -3991.5 | N67: RISE INTERNATIONAL GROUP LIMITED | P67: BOOK TRANSFER CREDIT 41BOOK CREDIT MELTWATER NEWS US INC*ORG:ULUTECH IN TERNATIONAL TRADING LLC,2F 011 OBAID BUD NAIF *OGB:EMIRATES NBD BANK PJ,DUBAI BANIYAS ROAD*BNF:MELTWATER NEWS US INC,REDWOOD CITY CA/US,STE 165*OB I:INS151564791*STBOOK*TIME:0622*YOUR REF:EPHCOP16603XIGD9*OUR REF:166272624
A68: 102 - US | B68: 45786 | C68: =UPPER(TEXT(B68, "[$-en-US]mmmm")) -> MAY | D68: =YEAR(B68) -> 2025 | E68: =VLOOKUP(A68,Sheet2!A:B,2,0) -> Americas | F68: Deposited | G68: PMT-S151-205267 | I68: USD | J68: -3990 | K68: -3990 | L68: 3990 | M68: -3990 | N68: OPERADORA HOTELERA DEL CORREDOR MAYAKOBA | P68: INCOMING MONEY TRANSFER 53RECD FED BANK OF AMERICA N.A.*ORG:1/OPERADORA HO TELERA DEL CORREDO,3/MX/MEXICO,2/PLAYA DEL*OGB:BBVA BANCOMER,S.A.,MEXICO,120 0,AVENIDA UNIVERSIDAD*BNF:MELTWATER NEWS US INC,REDWOOD CITY CA/US,2 75 SHO*OBI:444*STFEDSEQ:B1Q8982R000314*TIME:2216*YOUR REF:1074658586010177*OU R REF:129062691
A69: 102 - US | B69: 44945 | C69: =UPPER(TEXT(B69, "[$-en-US]mmmm")) -> JANUARY | D69: =YEAR(B69) -> 2023 | E69: =VLOOKUP(A69,Sheet2!A:B,2,0) -> Americas | F69: Deposited | G69: PMT-S151-161929 | I69: USD | J69: -3950 | K69: -3950 | L69: 3950 | M69: -3950 | N69: CommunityAmerica Credit Union | P69: ACH CONCENTRATION CREDIT ACH CORP TRADE PAYMENT FROM COMMUNITYAMERICA COMMUNITY DIRECT-PAY 30422800
A70: 102 - US | B70: 45987 | C70: =UPPER(TEXT(B70, "[$-en-US]mmmm")) -> NOVEMBER | D70: =YEAR(B70) -> 2025 | E70: =VLOOKUP(A70,Sheet2!A:B,2,0) -> Americas | F70: Deposited | G70: PMT-S151-214621 | I70: USD | J70: -3841.2 | K70: -3841.2 | L70: 3841.2 | M70: 154725.09 | N70: Amazon.com Services LLC | P70: ACH CONCENTRATION CREDIT ACH CASH CONCENTRATION AMAZON.COM-EDI PYMNTS AMAZON.CO EDI PYMNTS DASACDYOVX4SPOU
A71: 102 - US | B71: 44823 | C71: =UPPER(TEXT(B71, "[$-en-US]mmmm")) -> SEPTEMBER | D71: =YEAR(B71) -> 2022 | E71: =VLOOKUP(A71,Sheet2!A:B,2,0) -> Americas | F71: Deposited | G71: PMT-S151-154377 | H71: IN-S151-543872 | I71: USD | J71: -30844.22 | K71: -30844.22 | L71: 3520.22 | M71: -3520.22 | N71: AIDS Healthcare Foundation | O71: Jose Castellanos-103 | P71: PMT-S151-153768 (09/06/2022)
A72: 102 - US | B72: 46108 | C72: =UPPER(TEXT(B72, "[$-en-US]mmmm")) -> MARCH | D72: =YEAR(B72) -> 2026 | E72: =VLOOKUP(A72,Sheet2!A:B,2,0) -> Americas | F72: Deposited | G72: PMT-S151-221854 | I72: USD | J72: -3500 | K72: -3500 | L72: 3500 | M72: -250567.82 | N72: DUMMY CUSTOMER_CASHAPPS 102 - US | P72: ACH CONCENTRATION CREDIT ACH CASH CONCENTRATION AMERICAN INDIAN-AMINDIAN American AMINDIAN 3441
A73: 102 - US | B73: 44715 | C73: =UPPER(TEXT(B73, "[$-en-US]mmmm")) -> JUNE | D73: =YEAR(B73) -> 2022 | E73: =VLOOKUP(A73,Sheet2!A:B,2,0) -> Americas | F73: Deposited | G73: PMT-S151-148522 | I73: USD | J73: -3450.01 | K73: -3450.01 | L73: 3450.01 | M73: -3450.01 | N73: Peak Vista Community Health Centers | P73: ACH CONCENTRATION CREDIT ACH CASH CONCENTRATION PEAK VISTA COMM-TRADE PAY Peak Vist TRADE PAY VMEL03
A74: 102 - US | B74: 44778 | C74: =UPPER(TEXT(B74, "[$-en-US]mmmm")) -> AUGUST | D74: =YEAR(B74) -> 2022 | E74: =VLOOKUP(A74,Sheet2!A:B,2,0) -> Americas | F74: Deposited | G74: PMT-S151-152042 | I74: USD | J74: -3400 | K74: -3400 | L74: 3400 | M74: -3400 | N74: iProspect Colombia S.A.S | O74: Yangzom Vitali | P74: INCOMING MONEY TRANSFER 53RECD FED BANK OF AMERICA N.A.*ORG:IPROSPECT COLO MBIA SAS,BOGOTA COLOMBIA,CARRERA 19 C 91 6*OGB:SCOTIABANK COLPATRIA S.A.,BOGO TA,TORRE COLPATRIA,CARRERA*BNF:MELTWATER NEWS US INC,SAN FRANCISCO CA/ US,STE 100*OBI:ACC INVOICE IN-S151-533120*STFEDSEQ:B1Q8981R003908*TIME:1848*Y OUR REF:KTPP2090515*OUR REF:217618348
A75: 102 - US | B75: 44679 | C75: =UPPER(TEXT(B75, "[$-en-US]mmmm")) -> APRIL | D75: =YEAR(B75) -> 2022 | E75: =VLOOKUP(A75,Sheet2!A:B,2,0) -> Americas | F75: Deposited | G75: PMT-S151-146617 | H75: IN-S151-536351 | I75: USD | J75: -6750 | K75: -6750 | L75: 3375 | M75: -3375 | N75: American Oncology Network | O75: Jose Castellanos | P75: Check
A76: 102 - US | B76: 44750 | C76: =UPPER(TEXT(B76, "[$-en-US]mmmm")) -> JULY | D76: =YEAR(B76) -> 2022 | E76: =VLOOKUP(A76,Sheet2!A:B,2,0) -> Americas | F76: Deposited | G76: PMT-S151-150272 | I76: USD | J76: -3300 | K76: -3300 | L76: 3300 | M76: -3300 | N76: Fishburne Military School | O76: Jose Castellanos | P76: CHECK
A77: 102 - US | B77: 46146 | C77: =UPPER(TEXT(B77, "[$-en-US]mmmm")) -> MAY | D77: =YEAR(B77) -> 2026 | E77: =VLOOKUP(A77,Sheet2!A:B,2,0) -> Americas | F77: Deposited | G77: PMT-S151-223743 | I77: USD | J77: -3187.5 | K77: -3187.5 | L77: 3187.5 | M77: -3187.5 | N77: The Hanover Insurance Company
A78: 102 - US | B78: 44694 | C78: =UPPER(TEXT(B78, "[$-en-US]mmmm")) -> MAY | D78: =YEAR(B78) -> 2022 | E78: =VLOOKUP(A78,Sheet2!A:B,2,0) -> Americas | F78: Deposited | G78: PMT-S151-147510 | H78: IN-S151-536994 | I78: USD | J78: -6000 | K78: -6000 | L78: 3000 | M78: -3000 | N78: High Bar Brands | O78: Stephanie Thore | P78: CHECK
A79: 102 - US | B79: 45084 | C79: =UPPER(TEXT(B79, "[$-en-US]mmmm")) -> JUNE | D79: =YEAR(B79) -> 2023 | E79: =VLOOKUP(A79,Sheet2!A:B,2,0) -> Americas | F79: Deposited | G79: PMT-S151-169389 | I79: USD | J79: -2979 | K79: -2979 | L79: 2979 | M79: -250567.82 | N79: DUMMY CUSTOMER_CASHAPPS 102 - US | P79: FOREIGN REMITTANCE CREDIT 33RECD CHIP DEUTSCHE BANK AG*ORG:EPPENDORF NEDERLAND B .V.,NETHERLANDS-NL,6546 BC NIJMEGE*OGB:DEUTSCHE BANK AG,AMSTERDAM,DE ENTREE 196*BNF:MELTWATER NEWS US INC,REDWOOD CITY CA/US,STE 165*OBI:2023-400 -003 05/01/23*STCHIPSEQ:0022320*TIME:0000*YOUR REF:SIP/02.06-10:52*OUR REF:15 8317944
A80: 102 - US | B80: 45883 | C80: =UPPER(TEXT(B80, "[$-en-US]mmmm")) -> AUGUST | D80: =YEAR(B80) -> 2025 | E80: =VLOOKUP(A80,Sheet2!A:B,2,0) -> Americas | F80: Deposited | G80: PMT-S151-209465 | H80: IN-S151-584586 | I80: USD | J80: -36131.26 | K80: -36131.26 | L80: 2963.26 | M80: -2963.26 | N80: L.A. Care Health Plan | O80: Jose Castellanos | P80: ACH CONCENTRATION CREDIT ACH CASH CONCENTRATION L.A. CARE HEALTH-122000661
A81: 102 - US | B81: 45866 | C81: =UPPER(TEXT(B81, "[$-en-US]mmmm")) -> JULY | D81: =YEAR(B81) -> 2025 | E81: =VLOOKUP(A81,Sheet2!A:B,2,0) -> Americas | F81: Deposited | G81: PMT-S151-208422 | I81: USD | J81: -2636.66 | K81: -2636.66 | L81: 2636.66 | M81: -2636.66 | N81: Survivors Network of those Abused by Priests (SNAP)
A82: 102 - US | B82: 45884 | C82: =UPPER(TEXT(B82, "[$-en-US]mmmm")) -> AUGUST | D82: =YEAR(B82) -> 2025 | E82: =VLOOKUP(A82,Sheet2!A:B,2,0) -> Americas | F82: Deposited | G82: PMT-S151-209557 | I82: USD | J82: -2625 | K82: -2625 | L82: 2625 | M82: -2625 | N82: Green Check Verified | P82: ACH CONCENTRATION CREDIT ACH CASH CONCENTRATION GREEN CHECK VERI-MERCURYACH Green Che MercuryACH MRCR-QVA1TXX X5U
A83: 102 - US | B83: 44992 | C83: =UPPER(TEXT(B83, "[$-en-US]mmmm")) -> MARCH | D83: =YEAR(B83) -> 2023 | E83: =VLOOKUP(A83,Sheet2!A:B,2,0) -> Americas | F83: Deposited | G83: PMT-S151-164531 | I83: USD | J83: -2550 | K83: -2550 | L83: 2550 | M83: -250567.82 | N83: DUMMY CUSTOMER_CASHAPPS 102 - US | P83: ACH CONCENTRATION CREDIT ACH CORP TRADE PAYMENT FROM HOPE GAS,INC. HOPE GAS,PAYMENTS 188413095
A84: 102 - US | B84: 44733 | C84: =UPPER(TEXT(B84, "[$-en-US]mmmm")) -> JUNE | D84: =YEAR(B84) -> 2022 | E84: =VLOOKUP(A84,Sheet2!A:B,2,0) -> Americas | F84: Deposited | G84: PMT-S151-149275 | I84: USD | J84: -2425 | K84: -2425 | L84: 2425 | M84: -2425 | N84: Matrix LLC | P84: CHECK
A85: 102 - US | B85: 45933 | C85: =UPPER(TEXT(B85, "[$-en-US]mmmm")) -> OCTOBER | D85: =YEAR(B85) -> 2025 | E85: =VLOOKUP(A85,Sheet2!A:B,2,0) -> Americas | F85: Deposited | G85: PMT-S151-211737 | H85: IN-S151-586645 | I85: USD | J85: -2500 | K85: -2500 | L85: 2300 | M85: -2300 | N85: Thunder Tech | P85: ACH CONCENTRATION CREDIT ACH CASH CONCENTRATION THUNDERTECH-9.30.25 THUNDERTE 9.30.25 MELTWATER
A86: 102 - US | B86: 45209 | C86: =UPPER(TEXT(B86, "[$-en-US]mmmm")) -> OCTOBER | D86: =YEAR(B86) -> 2023 | E86: =VLOOKUP(A86,Sheet2!A:B,2,0) -> Americas | F86: Deposited | G86: PMT-S151-176048 | H86: IN-S151-560145 | I86: USD | J86: -6360.82 | K86: -6360.82 | L86: 2259.39 | M86: -2259.39 | N86: National Sorghum Producers | P86: CHECK
A87: 102 - US | B87: 45202 | C87: =UPPER(TEXT(B87, "[$-en-US]mmmm")) -> OCTOBER | D87: =YEAR(B87) -> 2023 | E87: =VLOOKUP(A87,Sheet2!A:B,2,0) -> Americas | F87: Deposited | G87: PMT-S151-175765 | I87: USD | J87: -2177.51 | K87: -2177.51 | L87: 2177.51 | M87: -2177.51 | N87: Insight Venture Management | O87: Jason Welch | P87: ACH CONCENTRATION CREDIT ACH CORP TRADE PAYMENT FROM INSIGHT VENTURE INSIGHT V DIRECT-PAY 53852876
A88: 102 - US | B88: 46098 | C88: =UPPER(TEXT(B88, "[$-en-US]mmmm")) -> MARCH | D88: =YEAR(B88) -> 2026 | E88: =VLOOKUP(A88,Sheet2!A:B,2,0) -> Americas | F88: Deposited | G88: PMT-S151-221300 | I88: USD | J88: -2150 | K88: -2150 | L88: 2150 | M88: -250567.82 | N88: DUMMY CUSTOMER_CASHAPPS 102 - US | P88: ACH CONCENTRATION CREDIT ACH CASH CONCENTRATION AMERICAN FOREIGN-BILL.COM American Bill.com 015MRNWKHRWP 41O
A89: 102 - US | B89: 44869 | C89: =UPPER(TEXT(B89, "[$-en-US]mmmm")) -> NOVEMBER | D89: =YEAR(B89) -> 2022 | E89: =VLOOKUP(A89,Sheet2!A:B,2,0) -> Americas | F89: Deposited | G89: PMT-S151-157433 | I89: USD | J89: -2085 | K89: -2085 | L89: 2085 | M89: -250567.82 | N89: DUMMY CUSTOMER_CASHAPPS 102 - US | P89: ACH CONCENTRATION CREDIT ACH CASH CONCENTRATION UNITED NATIONS-3305888902 UNITED NA 3305888902 3305888902
A90: 102 - US | B90: 44848 | C90: =UPPER(TEXT(B90, "[$-en-US]mmmm")) -> OCTOBER | D90: =YEAR(B90) -> 2022 | E90: =VLOOKUP(A90,Sheet2!A:B,2,0) -> Americas | F90: Deposited | G90: PMT-S151-156027 | I90: USD | J90: -2032.49 | K90: -2032.49 | L90: 2032.49 | M90: -2032.49 | N90: Feeding Westchester | P90: CHECK
A91: 102 - US | B91: 45194 | C91: =UPPER(TEXT(B91, "[$-en-US]mmmm")) -> SEPTEMBER | D91: =YEAR(B91) -> 2023 | E91: =VLOOKUP(A91,Sheet2!A:B,2,0) -> Americas | F91: Deposited | G91: PMT-S151-175314 | H91: IN-S151-559407 | I91: USD | J91: -4000 | K91: -4000 | L91: 2000 | M91: -2000 | N91: BioSTL | P91: ACH CONCENTRATION CREDIT ACH CASH CONCENTRATION BIOGENFU1 3638-PAYMENTS BIOGENFU1 PAYMENTS Meltwater News
A92: 102 - US | B92: 45593 | C92: =UPPER(TEXT(B92, "[$-en-US]mmmm")) -> OCTOBER | D92: =YEAR(B92) -> 2024 | E92: =VLOOKUP(A92,Sheet2!A:B,2,0) -> Americas | F92: Deposited | G92: PMT-S151-195665 | H92: IN-S151-574748 | I92: USD | J92: -22000 | K92: -22000 | L92: 2000 | M92: -2000 | N92: Cover Genius Trading Pty Ltd | P92: COVER GENIUS HOLDINGS PTY LTD COUPA PAY 821-2622 COVER GENIUS HOL DINGS PTY LTD TMATE /ROC/12397127124613 FX USD 22000.00 AT 0.6756200 200226969/TMS/2024-10-27T21:33:18 GMT/MID/0.661282
A93: 102 - US | B93: 44872 | C93: =UPPER(TEXT(B93, "[$-en-US]mmmm")) -> NOVEMBER | D93: =YEAR(B93) -> 2022 | E93: =VLOOKUP(A93,Sheet2!A:B,2,0) -> Americas | F93: Deposited | G93: PMT-S151-157478 | I93: USD | J93: -1800 | K93: -1800 | L93: 1800 | M93: -1800 | N93: Concord University | O93: Jose Castellanos-103 | P93: IN-S151-544931 got credited CM-S151-13155
A94: 102 - US | B94: 46003 | C94: =UPPER(TEXT(B94, "[$-en-US]mmmm")) -> DECEMBER | D94: =YEAR(B94) -> 2025 | E94: =VLOOKUP(A94,Sheet2!A:B,2,0) -> Americas | F94: Deposited | G94: PMT-S151-215552 | I94: USD | J94: -1750 | K94: -1750 | L94: 1750 | M94: -250567.82 | N94: DUMMY CUSTOMER_CASHAPPS 102 - US | P94: ACH CONCENTRATION CREDIT ACH CASH CONCENTRATION ELEVATED CULTIVA-E CULT ELEVATED E CULT E CULTIVATION
A95: 102 - US | B95: 44862 | C95: =UPPER(TEXT(B95, "[$-en-US]mmmm")) -> OCTOBER | D95: =YEAR(B95) -> 2022 | E95: =VLOOKUP(A95,Sheet2!A:B,2,0) -> Americas | F95: Deposited | G95: PMT-S151-157014 | I95: USD | J95: -1500 | K95: -1500 | L95: 1500 | M95: -250567.82 | N95: DUMMY CUSTOMER_CASHAPPS 102 - US | P95: ACH CONCENTRATION CREDIT ACH CORP TRADE PAYMENT FROM LAWRENCE LIV NAT LAWRENCE PAYABLES LAWRENCE LIVERM
A96: 102 - US | B96: 45960 | C96: =UPPER(TEXT(B96, "[$-en-US]mmmm")) -> OCTOBER | D96: =YEAR(B96) -> 2025 | E96: =VLOOKUP(A96,Sheet2!A:B,2,0) -> Americas | F96: Deposited | G96: PMT-S151-213059 | I96: USD | J96: -1500 | K96: -1500 | L96: 1500 | M96: -1500 | N96: Echelon Insights | O96: Yangzom Vitali-116 | P96: FOREIGN REMITTANCE CREDIT 33RECD CHIP PNC BANK*ORG:ECHELON INSIGHTS LLC,ALEX ANDRIA VA 22314 3029 US,STE 250*OGB:PNC BANK,N.A.,US/CAMP HILL,17001-0297,PA 500 FIRST AVEN*BNF:MELTWATER NEWS US INC,REDWOOD CITY CA/US,275 SHO* BBI:/INT/202510884077*STCHIPSEQ:00158840*TIME:0111*YOUR REF:IN-S151-587978*OU R REF:303170378
A97: 102 - US | B97: 46038 | C97: =UPPER(TEXT(B97, "[$-en-US]mmmm")) -> JANUARY | D97: =YEAR(B97) -> 2026 | E97: =VLOOKUP(A97,Sheet2!A:B,2,0) -> Americas | F97: Deposited | G97: PMT-S151-217537 | I97: USD | J97: -1498.72 | K97: -1498.72 | L97: 1498.72 | M97: -1498.72 | N97: Elevate Textiles | P97: ACH CONCENTRATION CREDIT ACH CORP TRADE PAYMENT FROM ELEVATE TEXTILES ELEVATE T CORP PMT 488174
A98: 102 - US | B98: 46143 | C98: =UPPER(TEXT(B98, "[$-en-US]mmmm")) -> MAY | D98: =YEAR(B98) -> 2026 | E98: =VLOOKUP(A98,Sheet2!A:B,2,0) -> Americas | F98: Deposited | G98: PMT-S151-223677 | I98: USD | J98: -1450 | K98: -1450 | L98: 1450 | M98: -1450 | N98: Celigo CAM USD
A99: 102 - US | B99: 45533 | C99: =UPPER(TEXT(B99, "[$-en-US]mmmm")) -> AUGUST | D99: =YEAR(B99) -> 2024 | E99: =VLOOKUP(A99,Sheet2!A:B,2,0) -> Americas | F99: Deposited | G99: PMT-S151-192922 | I99: USD | J99: -1379.91 | K99: -1379.91 | L99: 1379.91 | M99: -250567.82 | N99: DUMMY CUSTOMER_CASHAPPS 102 - US | P99: ACH CONCENTRATION CREDIT ACH CASH CONCENTRATION DANIEL J EDELMAN-PAYMENTS Daniel J PAYMENTS 01VEND031547 USD
A100: 102 - US | B100: 46080 | C100: =UPPER(TEXT(B100, "[$-en-US]mmmm")) -> FEBRUARY | D100: =YEAR(B100) -> 2026 | E100: =VLOOKUP(A100,Sheet2!A:B,2,0) -> Americas | F100: Deposited | G100: PMT-S151-220382 | H100: IN-S151-592980 | I100: USD | J100: -46120.26 | K100: -46120.26 | L100: 1320.26 | M100: -1320.26 | N100: Adobe Inc | P100: ACH CONCENTRATION CREDIT ACH CASH CONCENTRATION ADOBE INC.-PAYMENTS Adobe Inc PAYMENTS 5101172354
...

Sheet Copy Netsuite Report
A1: Subsidiary (no hierarchy) | B1: Date | C1: Status | D1: Number | E1: Invoice Number | F1: Currency | G1: Amount Base | H1: Amount USD | I1: Amount Remaining | J1: Balance | K1: Customer Name | L1: AR Specialist | M1: Memo
A2: 102 - US | B2: 45736 | C2: Deposited | D2: PMT-S151-202999 | F2: USD | G2: -81229.11 | H2: -81229.11 | I2: 81229.11 | J2: -250567.82 | K2: DUMMY CUSTOMER_CASHAPPS 102 - US | M2: ACH CONCENTRATION CREDIT ACH CORP TRADE PAYMENT FROM MICROSOFT MICROSOFT 0004992933 68251185441010
A3: 102 - US | B3: 45922 | C3: Deposited | D3: PMT-S151-211138 | F3: USD | G3: -54445.55 | H3: -54445.55 | I3: 54445.55 | J3: -50095.55 | K3: Microsoft Corporation | M3: ACH CONCENTRATION CREDIT ACH CORP TRADE PAYMENT FROM MICROSOFT MICROSOFT 0005317824 68550845931010
A4: 102 - US | B4: 46071 | C4: Deposited | D4: PMT-S151-219775 | F4: USD | G4: -35534 | H4: -35534 | I4: 35534 | J4: -35534 | K4: Brick Media | M4: INCOMING MONEY TRANSFER 53RECD FED JPMORGAN CHASE BANK*ORG:BRICK MEDIA LLC,RO CKY RIVER OH 44116-1815 US,19885 DETRO*OGB:JPMORGAN CHASE BANK,TAMPA,10410 HI GHLAND MANOR DRIVE*BNF:MELTWATER NEWS US INC,REDWOOD CITY CA/US,275 S HO*STFEDSEQ:B1Q8982R000363*TIME:0341*YOUR REF:WTH OF 26/02/18*OUR REF:0490937 10
A5: 102 - US | B5: 45691 | C5: Deposited | D5: PMT-S151-200395 | F5: USD | G5: -32613.85 | H5: -32613.85 | I5: 32613.85 | J5: -250567.82 | K5: DUMMY CUSTOMER_CASHAPPS 102 - US | M5: ACH CONCENTRATION CREDIT ACH CORP TRADE PAYMENT FROM MICROSOFT MICROSOFT 0004890122 68550745441010
A6: 102 - US | B6: 44851 | C6: Deposited | D6: PMT-S151-156272 | F6: USD | G6: -27218.77 | H6: -27218.77 | I6: 27218.77 | J6: -27218.77 | K6: ComplySci | M6: ACH CONCENTRATION CREDIT ACH CASH CONCENTRATION COMPLYSCI-PAYMENT ComplySci Payment 46810
A7: 102 - US | B7: 45856 | C7: Deposited | D7: PMT-S151-208003 | F7: USD | G7: -25699.72 | H7: -25699.72 | I7: 25699.72 | J7: -250567.82 | K7: DUMMY CUSTOMER_CASHAPPS 102 - US | M7: ACH CONCENTRATION CREDIT ACH CASH CONCENTRATION ENVIOLOL-PAYMENTS ENVIOLOL PAYMENTS 0000010593
A8: 102 - US | B8: 45838 | C8: Deposited | D8: PMT-S151-207105 | F8: USD | G8: -24128 | H8: -24128 | I8: 24128 | J8: -250567.82 | K8: DUMMY CUSTOMER_CASHAPPS 102 - US | M8: ACH CONCENTRATION CREDIT ACH CORP TRADE PAYMENT FROM MICROSOFT MICROSOFT 0005162418 68500854311010
A9: 102 - US | B9: 46118 | C9: Deposited | D9: PMT-S151-222326 | F9: USD | G9: -20913.77 | H9: -20913.77 | I9: 20913.77 | J9: -20913.77 | K9: Camp Chef | M9: ACH CONCENTRATION CREDIT ACH CASH CONCENTRATION BUSHNELL OPER-PAYMENT BUSHNELL PAYMENT 2021416
A10: 102 - US | B10: 46127 | C10: Deposited | D10: PMT-S151-222780 | F10: USD | G10: -20698 | H10: -20698 | I10: 20698 | J10: -20698 | K10: Culloton + Bauer Luce | M10: ACH CONCENTRATION CREDIT ACH CASH CONCENTRATION CULLOTON STRATEG-ACH PAYMEN Culloton ACH Paymen 95267
A11: 102 - US | B11: 45889 | C11: Deposited | D11: PMT-S151-209700 | F11: USD | G11: -20000 | H11: -20000 | I11: 20000 | J11: -50095.55 | K11: Microsoft Corporation | M11: ACH CONCENTRATION CREDIT ACH CORP TRADE PAYMENT FROM MICROSOFT MICROSOFT 0005263117 68151120631010
A12: 102 - US | B12: 46108 | C12: Deposited | D12: PMT-S151-221843 | E12: PMT-S151-221843 | F12: USD | G12: -39600 | H12: -39600 | I12: 19800 | J12: -19800 | K12: Blue Learning | M12: ACH CONCENTRATION CREDIT ACH CASH CONCENTRATION BLUE LEARNING OP-CORP PAY BLUE LEAR CORP PAY 10957
A13: 102 - US | B13: 46108 | C13: Deposited | D13: PMT-S151-221843 | E13: IN-S151-593360 | F13: USD | G13: -39600 | H13: -39600 | I13: 19800 | J13: -19800 | K13: Blue Learning | M13: ACH CONCENTRATION CREDIT ACH CASH CONCENTRATION BLUE LEARNING OP-CORP PAY BLUE LEAR CORP PAY 10957
A14: 102 - US | B14: 46139 | C14: Deposited | D14: PMT-S151-223322 | F14: USD | G14: -19350 | H14: -19350 | I14: 19350 | J14: -19350 | K14: Gaudenzia, Inc
A15: 102 - US | B15: 45049 | C15: Deposited | D15: PMT-S151-167535 | F15: USD | G15: -18060 | H15: -18060 | I15: 18060 | J15: -18060 | K15: Sun Valley Resort | M15: CHECK
A16: 102 - US | B16: 44652 | C16: Deposited | D16: PMT-S151-145279 | F16: USD | G16: -17850.4 | H16: -17850.4 | I16: 17850.4 | J16: -17850.4 | K16: Netchoice | M16: FOREIGN REMITTANCE CREDIT 33RECD CHIP WELLS FARGO BANK,SAN FRANCISCO,CA*O RG:NETCHOICE,US 20005-3417,WASHINGTON DC,1401 K S*BNF:MELTWATER NEW S US INC,SAN FRANCISCO CA/US,STE 100*OBI:INVOICE S151 535230*STCHIPSEQ :0499781*TIME:1511*YOUR REF:643*OUR REF:091587415
A17: 102 - US | B17: 46132 | C17: Deposited | D17: PMT-S151-223019 | F17: USD | G17: -17200 | H17: -17200 | I17: 17200 | J17: 0 | K17: Gordon State College | M17: ACH CONCENTRATION CREDIT ACH CORP TRADE PAYMENT FROM Gordon State Col Gordon St CTX 0000039074
A18: 102 - US | B18: 44907 | C18: Deposited | D18: PMT-S151-159463 | F18: USD | G18: -16500 | H18: -16500 | I18: 16500 | J18: 3500 | K18: Bayhealth Medical Center | M18: CHECK
A19: 102 - US | B19: 46143 | C19: Deposited | D19: PMT-S151-223708 | F19: USD | G19: -16483 | H19: -16483 | I19: 16483 | J19: -16483 | K19: Washington Times Global Media Group | L19: Jordan Irvine | M19: ACH CREDIT ACH DEPOSIT FROM WASHINGTON TIMES-CREDITS WASHINGTO CREDITS TWT-22920
A20: 102 - US | B20: 46056 | C20: Deposited | D20: PMT-S151-218617 | E20: IN-S151-589402 | F20: USD | G20: -16000 | H20: -16000 | I20: 15999.84 | J20: -15999.84 | K20: West Palm Beach Downtown Development Authority | L20: Jose Castellanos
A21: 102 - US | B21: 44680 | C21: Deposited | D21: PMT-S151-146709 | F21: USD | G21: -15750 | H21: -15750 | I21: 15750 | J21: -15750 | K21: Kean University | L21: Kristin Walsh
A22: 102 - US | B22: 46139 | C22: Deposited | D22: PMT-S151-223397 | F22: USD | G22: -15000 | H22: -15000 | I22: 15000 | J22: -15000 | K22: Nautilus Solar Energy, LLC | M22: ACH CONCENTRATION CREDIT ACH CASH CONCENTRATION NAUTILUS SOLAR E-ACH PMT NAUTILUS ACH Pmt 11216430243
A23: 102 - US | B23: 45996 | C23: Deposited | D23: PMT-S151-215069 | F23: USD | G23: -14145.99 | H23: -14145.99 | I23: 14145.99 | J23: 154725.09 | K23: Amazon.com Services LLC | M23: ACH CONCENTRATION CREDIT ACH CASH CONCENTRATION AMAZON.COM-EDI PYMNTS AMAZON.CO EDI PYMNTS DAS4VG6U2FWEEBQ
A24: 102 - US | B24: 45614 | C24: Deposited | D24: PMT-S151-196679 | F24: USD | G24: -13975 | H24: -13975 | I24: 13975 | J24: -250567.82 | K24: DUMMY CUSTOMER_CASHAPPS 102 - US | M24: FOREIGN REMITTANCE CREDIT 33RECD CHIP JPMORGAN CHASE BANK*ORG:BYTECHIP LLC,UNITED STATES,US ,8 THE GREEN, SUITE B, DOVE*OGB:RD WALLET TECHNOLOGIES LIMITED,CAUSEWAY BAY,535 JAFFE RO*BNF:MELTWATER NEWS US INC,REDWOOD CITY CA/US,STE 165*OBI:202411080803*STCHIPSEQ:00209649*TIME:0248 *YOUR REF:1513OT8581513*OUR REF:323200531
A25: 102 - US | B25: 44694 | C25: Deposited | D25: PMT-S151-147498 | F25: USD | G25: -13650 | H25: -13650 | I25: 13650 | J25: -13650 | K25: Florida Dept. of Agriculture and Consumer Services | L25: Jordan Irvine | M25: CHECK
A26: 102 - US | B26: 45910 | C26: Deposited | D26: PMT-S151-210583 | F26: USD | G26: -13564.62 | H26: -13564.62 | I26: 13564.62 | J26: -13564.62 | K26: Cubic Corporation | L26: Jose Castellanos | M26: Customer refund ACH CONCENTRATION CREDIT ACH CASH CONCENTRATION CUBIC CORPORATIO-EDI/ACH Cubic Cor EDI/ACH 10152000245 624
A27: 102 - US | B27: 45167 | C27: Deposited | D27: PMT-S151-173898 | F27: USD | G27: -13500 | H27: -13500 | I27: 13500 | J27: -13500 | K27: Versant Health | M27: CHECK
A28: 102 - US | B28: 45085 | C28: Deposited | D28: PMT-S151-169476 | F28: USD | G28: -12980 | H28: -12980 | I28: 12980 | J28: -250567.82 | K28: DUMMY CUSTOMER_CASHAPPS 102 - US | M28: ACH CONCENTRATION CREDIT ACH CASH CONCENTRATION DALLAS FOUNDATIO-CORP PAY DALLAS FO CORP PAY 1504
A29: 102 - US | B29: 44830 | C29: Deposited | D29: PMT-S151-154814 | F29: USD | G29: -11550 | H29: -11550 | I29: 11550 | J29: -11550 | K29: AmeriCU Credit Union | M29: CHECK
A30: 102 - US | B30: 45174 | C30: Deposited | D30: PMT-S151-174242 | E30: IN-S151-555435 | F30: USD | G30: -22698.13 | H30: -22698.13 | I30: 11349.07 | J30: -11349.07 | K30: Drive Agency, LLC | L30: Yangzom Vitali-116 | M30: ACH CREDIT ACH DEPOSIT FROM GREENBERG QUINLA-ACH PAYMNT INV IN-S151-548883
A31: 102 - US | B31: 46136 | C31: Deposited | D31: PMT-S151-223327 | F31: USD | G31: -9900 | H31: -9900 | I31: 9900 | J31: -250567.82 | K31: DUMMY CUSTOMER_CASHAPPS 102 - US | M31: ACH CONCENTRATION CREDIT ACH CASH CONCENTRATION COMMISSION L'UNI-PAYMENT COMMISSIO PAYMENT KQ3LUSEQGD69
A32: 102 - US | B32: 45114 | C32: Deposited | D32: PMT-S151-171074 | F32: USD | G32: -9695 | H32: -9695 | I32: 9695 | J32: -10420 | K32: Amarin Pharma, Inc. | L32: Sarah Shoemaker-MW | M32: FOREIGN REMITTANCE CREDIT 33RECD CHIP JPMORGAN CHASE BANK*ORG:AMARIN SWITZERLAND GMBH,CH/ZUG 6300,BAARERSTRASSE 75*OGB:JPMORGAN CHASE BANK,N.A.,ZUERICH,DREI KOENIGSTRASSE 21*BNF:MELTWATER NEWS US INC,REDWOOD CITY CA/US,STE 165 *OBI:/ROC/714*STCHIPSEQ:0157130*TIME:0207*YOUR REF:SWF OF 23/07/07*OUR REF:18 8409072
A33: 102 - US | B33: 45684 | C33: Deposited | D33: PMT-S151-199815 | F33: USD | G33: -9680 | H33: -9680 | I33: 9680 | J33: -9680 | K33: Zonda Home | M33: ACH CONCENTRATION CREDIT ACH CASH CONCENTRATION METROSTUDY INC-AB-TFBANIP METROSTUD AB-TFBANIP 4090116
A34: 102 - US | B34: 46031 | C34: Deposited | D34: PMT-S151-217064 | F34: USD | G34: -9600 | H34: -9600 | I34: 9600 | J34: -9600 | K34: Hunstville Botanical Garden | M34: ACH CONCENTRATION CREDIT ACH CASH CONCENTRATION HSV BG 517-ACH PAYMEN HSV BG ACH Paymen 32465974
A35: 102 - US | B35: 44852 | C35: Deposited | D35: PMT-S151-156313 | E35: IN-S151-546649 | F35: USD | G35: -14000 | H35: -14000 | I35: 9333.33 | J35: -9333.33 | K35: Management & Training Corporation (Job Corps) | L35: Jose Castellanos-103 | M35: renewal 12/7/22-12/6/25
A36: 102 - US | B36: 44736 | C36: Deposited | D36: PMT-S151-149470 | F36: USD | G36: -8250 | H36: -8250 | I36: 8250 | J36: -8250 | K36: Avendra | M36: CHECK
A37: 102 - US | B37: 44748 | C37: Deposited | D37: PMT-S151-150211 | F37: USD | G37: -8250 | H37: -8250 | I37: 8250 | J37: -250567.82 | K37: DUMMY CUSTOMER_CASHAPPS 102 - US | M37: ACH CONCENTRATION CREDIT ACH CASH CONCENTRATION INDIANA UNV-BATCH INDIANA U BATCH 504301824
A38: 102 - US | B38: 44956 | C38: Deposited | D38: PMT-S151-162604 | E38: IN-S151-549189 | F38: USD | G38: -15665.62 | H38: -15665.62 | I38: 8165.62 | J38: -8165.62 | K38: Comic Relief, Inc | M38: ACH CONCENTRATION CREDIT ACH CASH CONCENTRATION COMIC RELIEF8654-PAYMENTS COMIC REL PAYMENTS Meltwater N ews
A39: 102 - US | B39: 45856 | C39: Deposited | D39: PMT-S151-208027 | F39: USD | G39: -7720.17 | H39: -7720.17 | I39: 7720.17 | J39: -250567.82 | K39: DUMMY CUSTOMER_CASHAPPS 102 - US | M39: ACH CONCENTRATION CREDIT ACH CASH CONCENTRATION ENVIOLOL-PAYMENTS ENVIOLOL PAYMENTS 0000010634
A40: 102 - US | B40: 45881 | C40: Deposited | D40: PMT-S151-209317 | F40: USD | G40: -7652 | H40: -7652 | I40: 7652 | J40: -7652 | K40: Fort Worth Symphony Orchestra
A41: 102 - US | B41: 46126 | C41: Deposited | D41: PMT-S151-222677 | F41: USD | G41: -7500 | H41: -7500 | I41: 7500 | J41: -250567.82 | K41: DUMMY CUSTOMER_CASHAPPS 102 - US
A42: 102 - US | B42: 45205 | C42: Deposited | D42: PMT-S151-175978 | F42: USD | G42: -7350 | H42: -7350 | I42: 7350 | J42: -7350 | K42: American Magic | M42: ACH CONCENTRATION CREDIT ACH CASH CONCENTRATION BMQR-SPT ACH BMQR SPT ACH Meltwater
A43: 102 - US | B43: 45688 | C43: Deposited | D43: PMT-S151-200236 | F43: USD | G43: -7150 | H43: -7150 | I43: 7150 | J43: -250567.82 | K43: DUMMY CUSTOMER_CASHAPPS 102 - US | M43: ACH CONCENTRATION CREDIT ACH CORP TRADE PAYMENT FROM THE CITY OF NEW THE CITY Payments 202501296563717
A44: 102 - US | B44: 44838 | C44: Deposited | D44: PMT-S151-155504 | F44: USD | G44: -7000 | H44: -7000 | I44: 7000 | J44: -7000 | K44: Girl Scouts of Northeast Texas | M44: ACH CONCENTRATION CREDIT ACH CASH CONCENTRATION GIRL SCOUTS OF N-PAYMENTS GIRL SCOU PAYMENTS MELTWATER
A45: 102 - US | B45: 44897 | C45: Deposited | D45: PMT-S151-159053 | E45: IN-S151-547293 | F45: USD | G45: -20000 | H45: -20000 | I45: 7000 | J45: -7000 | K45: SSR Mining, Inc | M45: ACH CREDIT ACH DEPOSIT FROM SSR MINING INC.-AP PAYMENT SSR MININ AP PAYMENT NOTPROVIDED
A46: 102 - US | B46: 45138 | C46: Deposited | D46: PMT-S151-172289 | E46: IN-S151-568917 | F46: USD | G46: -7750 | H46: -7750 | I46: 6975 | J46: -6975 | K46: Johnston County Schools | L46: Stephanie Thore | M46: CHECK
A47: 102 - US | B47: 45128 | C47: Deposited | D47: PMT-S151-171846 | F47: USD | G47: -6929 | H47: -6929 | I47: 6929 | J47: -6929 | K47: Season Health | M47: ACH CONCENTRATION CREDIT ACH CASH CONCENTRATION SURELY HEALTH,I-TRANSFER
A48: 102 - US | B48: 46013 | C48: Deposited | D48: PMT-S151-216041 | E48: PMT-S151-216041 | F48: USD | G48: -6655 | H48: -6655 | I48: 6655 | J48: -6655 | K48: The Commit Partnership | M48: ACH CONCENTRATION CREDIT ACH CASH CONCENTRATION COMMIT2DALLAS-INS1515900
A49: 102 - US | B49: 44924 | C49: Deposited | D49: PMT-S151-160605 | F49: USD | G49: -6325 | H49: -6325 | I49: 6325 | J49: -6325 | K49: Gulfshore Playhouse | M49: CHECK
A50: 102 - US | B50: 46136 | C50: Deposited | D50: PMT-S151-223212 | F50: USD | G50: -6200 | H50: -6200 | I50: 6200 | J50: -6200 | K50: Honolulu Marathon Association | L50: Stephanie Thore
A51: 102 - US | B51: 46146 | C51: Deposited | D51: PMT-S151-223744 | F51: USD | G51: -5625 | H51: -5625 | I51: 5625 | J51: -5625 | K51: Omaha Supernovas
A52: 102 - US | B52: 44678 | C52: Deposited | D52: PMT-S151-146660 | F52: USD | G52: -5505 | H52: -5505 | I52: 5505 | J52: -5505 | K52: Pacvue | M52: ACH CONCENTRATION CREDIT ACH CASH CONCENTRATION PACVUE CORPORATI-ACH PMT PACVUE CO ACH Pmt 5332490959
A53: 102 - US | B53: 45041 | C53: Deposited | D53: PMT-S151-167020 | F53: USD | G53: -5500 | H53: -5500 | I53: 5500 | J53: -5500 | K53: Birmingham Public Schools | M53: CHECK
A54: 102 - US | B54: 45154 | C54: Deposited | D54: PMT-S151-173335 | F54: USD | G54: -5500 | H54: -5500 | I54: 5500 | J54: -5500 | K54: Brain Technologies, Inc. | M54: ACH CONCENTRATION CREDIT ACH CASH CONCENTRATION BRAIN TECHNOLOGI-BILL.COM Brain Tec Bill.com 016GNOXUE2QY ILR
A55: 102 - US | B55: 45952 | C55: Deposited | D55: PMT-S151-212527 | F55: USD | G55: -5500 | H55: -5500 | I55: 5500 | J55: -5500 | K55: Vladimir Jones
A56: 102 - US | B56: 44930 | C56: Deposited | D56: PMT-S151-160930 | F56: USD | G56: -5457 | H56: -5457 | I56: 5457 | J56: -5457 | K56: Calvin Klein | L56: Jason Welch | M56: INCOMING MONEY TRANSFER 53RECD FED BANK OF AMERICA N.A.*ORG:1/PVH EUROPE B .V.,3/NL/AMSTERDAM 1054ES,2/STADHOUDERSKAD*OGB:BANK OF AMERICA NA LONDON,LOND ON,BANK OF AMERICA MERRILL*BNF:MELTWATER NEWS US INC,SAN FRANCISCO CA/ US,STE 100*OBI:IN-S151-531453C PVHE CALVIN KL EIN EUROPE BV /RFB/221019200010 1556*STFEDSEQ:B1Q8982R002942*TIME:1618*YOUR REF:2210192000101556*OUR REF:0045 77450
A57: 102 - US | B57: 45342 | C57: Deposited | D57: PMT-S151-183645 | F57: USD | G57: -5400 | H57: -5400 | I57: 5400 | J57: -5400 | K57: Mextenis, S.A. de C.V | L57: Maria Papadopoulos | M57: INCOMING MONEY TRANSFER 53RECD FED BANK OF NEW YORK*ORG:MEX TENIS S.A. DE C.V.,MX 23/10/1992,BOSQUES DE LAS LOMA*OGB:INTERCAM BANCO SA INSTITUCION DE B A,CIUDAD DE MEXICO,COL*BNF:MELTWATER NEWS US INC,REDWOOD CITY CA/US,S TE 165*OBI:PAY LICENCIAMELTWATERPAQ PAGO DE SE RVIC BOF MEX TENIS S.A. DE C.V .*STFEDSEQ:B1Q8981R004078*TIME:1315*YOUR REF NONREF*OUR REF:051500808
A58: 102 - US | B58: 45763 | C58: Deposited | D58: PMT-S151-204303 | F58: USD | G58: -5375 | H58: -5375 | I58: 5375 | J58: -5375 | K58: Bath & Body Works Direct, Inc. | M58: ACH CONCENTRATION CREDIT ACH CASH CONCENTRATION L BRAND 1332-EDI PAYMNT L BRAND 1 EDI PAYMNT 2003275583
A59: 102 - US | B59: 45195 | C59: Deposited | D59: PMT-S151-175385 | E59: IN-S151-559205 | F59: USD | G59: -9717.12 | H59: -9717.12 | I59: 5254.62 | J59: -5254.62 | K59: CultureWorks Inc | M59: ACH CONCENTRATION CREDIT ACH CASH CONCENTRATION CULTUREWORKS,IN-BILL.COM CultureWo Bill.com 025BRMYDKVMZ 65U
A60: 102 - US | B60: 45828 | C60: Deposited | D60: PMT-S151-206730 | E60: IN-S151-583041 | F60: USD | G60: -55150 | H60: -55150 | I60: 5150 | J60: -50095.55 | K60: Microsoft Corporation | M60: ACH CONCENTRATION CREDIT ACH CASH CONCENTRATION 200-ACTIVISION P-6531011921 200-ACTIV 6531011921 6531011921
A61: 102 - US | B61: 45957 | C61: Deposited | D61: PMT-S151-212754 | F61: USD | G61: -5000 | H61: -5000 | I61: 5000 | J61: -5000 | K61: McDaniels Marketing
A62: 102 - US | B62: 45980 | C62: Deposited | D62: PMT-S151-214232 | F62: USD | G62: -5000 | H62: -5000 | I62: 5000 | J62: -5000 | K62: Mendaera, Inc
A63: 102 - US | B63: 44673 | C63: Deposited | D63: PMT-S151-146301 | F63: USD | G63: -4800 | H63: -4800 | I63: 4800 | J63: -4800 | K63: WeGo Public Transit | M63: CHECK
A64: 102 - US | B64: 46135 | C64: Deposited | D64: PMT-S151-223214 | F64: USD | G64: -4265.16 | H64: -4265.16 | I64: 4265.16 | J64: -4265.16 | K64: TFI Family Services, Inc. | M64: ACH CONCENTRATION CREDIT ACH CASH CONCENTRATION TFI FAMILY SERVI-ACH PAYMEN TFI Famil ACH Paymen V000000551
A65: 102 - US | B65: 44652 | C65: Deposited | D65: PMT-S151-145257 | F65: USD | G65: -4225 | H65: -4225 | I65: 4225 | J65: -4225 | K65: SVB Leerink | M65: ACH CONCENTRATION CREDIT ACH CASH CONCENTRATION LEERINK PRTNRS-TRADE PAY LEERINK P TRADE PAY MELTWATER
A66: 102 - US | B66: 45834 | C66: Deposited | D66: PMT-S151-206955 | F66: USD | G66: -4087.75 | H66: -4087.75 | I66: 4087.75 | J66: -4087.75 | K66: FOULGER-PRATT | M66: ACH CONCENTRATION CREDIT ACH CASH CONCENTRATION FOULGERPRATT PMD-PAYMENT FOULGERPR PAYMENT 5543440
A67: 102 - US | B67: 46143 | C67: Deposited | D67: PMT-S151-223676 | F67: USD | G67: -4026 | H67: -4026 | I67: 4026 | J67: 0 | K67: Philander Smith University | L67: Stephanie Thore
A68: 102 - US | B68: 45457 | C68: Deposited | D68: PMT-S151-189268 | E68: IN-S151-564791 | F68: USD | G68: -7983 | H68: -7983 | I68: 3991.5 | J68: -3991.5 | K68: RISE INTERNATIONAL GROUP LIMITED | M68: BOOK TRANSFER CREDIT 41BOOK CREDIT MELTWATER NEWS US INC*ORG:ULUTECH IN TERNATIONAL TRADING LLC,2F 011 OBAID BUD NAIF *OGB:EMIRATES NBD BANK PJ,DUBAI BANIYAS ROAD*BNF:MELTWATER NEWS US INC,REDWOOD CITY CA/US,STE 165*OB I:INS151564791*STBOOK*TIME:0622*YOUR REF:EPHCOP16603XIGD9*OUR REF:166272624
A69: 102 - US | B69: 45786 | C69: Deposited | D69: PMT-S151-205267 | F69: USD | G69: -3990 | H69: -3990 | I69: 3990 | J69: -3990 | K69: OPERADORA HOTELERA DEL CORREDOR MAYAKOBA | M69: INCOMING MONEY TRANSFER 53RECD FED BANK OF AMERICA N.A.*ORG:1/OPERADORA HO TELERA DEL CORREDO,3/MX/MEXICO,2/PLAYA DEL*OGB:BBVA BANCOMER,S.A.,MEXICO,120 0,AVENIDA UNIVERSIDAD*BNF:MELTWATER NEWS US INC,REDWOOD CITY CA/US,2 75 SHO*OBI:444*STFEDSEQ:B1Q8982R000314*TIME:2216*YOUR REF:1074658586010177*OU R REF:129062691
A70: 102 - US | B70: 44945 | C70: Deposited | D70: PMT-S151-161929 | F70: USD | G70: -3950 | H70: -3950 | I70: 3950 | J70: -3950 | K70: CommunityAmerica Credit Union | M70: ACH CONCENTRATION CREDIT ACH CORP TRADE PAYMENT FROM COMMUNITYAMERICA COMMUNITY DIRECT-PAY 30422800
A71: 102 - US | B71: 45987 | C71: Deposited | D71: PMT-S151-214621 | F71: USD | G71: -3841.2 | H71: -3841.2 | I71: 3841.2 | J71: 154725.09 | K71: Amazon.com Services LLC | M71: ACH CONCENTRATION CREDIT ACH CASH CONCENTRATION AMAZON.COM-EDI PYMNTS AMAZON.CO EDI PYMNTS DASACDYOVX4SPOU
A72: 102 - US | B72: 44823 | C72: Deposited | D72: PMT-S151-154377 | E72: IN-S151-543872 | F72: USD | G72: -30844.22 | H72: -30844.22 | I72: 3520.22 | J72: -3520.22 | K72: AIDS Healthcare Foundation | L72: Jose Castellanos-103 | M72: PMT-S151-153768 (09/06/2022)
A73: 102 - US | B73: 46108 | C73: Deposited | D73: PMT-S151-221854 | F73: USD | G73: -3500 | H73: -3500 | I73: 3500 | J73: -250567.82 | K73: DUMMY CUSTOMER_CASHAPPS 102 - US | M73: ACH CONCENTRATION CREDIT ACH CASH CONCENTRATION AMERICAN INDIAN-AMINDIAN American AMINDIAN 3441
A74: 102 - US | B74: 44715 | C74: Deposited | D74: PMT-S151-148522 | F74: USD | G74: -3450.01 | H74: -3450.01 | I74: 3450.01 | J74: -3450.01 | K74: Peak Vista Community Health Centers | M74: ACH CONCENTRATION CREDIT ACH CASH CONCENTRATION PEAK VISTA COMM-TRADE PAY Peak Vist TRADE PAY VMEL03
A75: 102 - US | B75: 44778 | C75: Deposited | D75: PMT-S151-152042 | F75: USD | G75: -3400 | H75: -3400 | I75: 3400 | J75: -3400 | K75: iProspect Colombia S.A.S | L75: Yangzom Vitali | M75: INCOMING MONEY TRANSFER 53RECD FED BANK OF AMERICA N.A.*ORG:IPROSPECT COLO MBIA SAS,BOGOTA COLOMBIA,CARRERA 19 C 91 6*OGB:SCOTIABANK COLPATRIA S.A.,BOGO TA,TORRE COLPATRIA,CARRERA*BNF:MELTWATER NEWS US INC,SAN FRANCISCO CA/ US,STE 100*OBI:ACC INVOICE IN-S151-533120*STFEDSEQ:B1Q8981R003908*TIME:1848*Y OUR REF:KTPP2090515*OUR REF:217618348
A76: 102 - US | B76: 44679 | C76: Deposited | D76: PMT-S151-146617 | E76: IN-S151-536351 | F76: USD | G76: -6750 | H76: -6750 | I76: 3375 | J76: -3375 | K76: American Oncology Network | L76: Jose Castellanos | M76: Check
A77: 102 - US | B77: 44750 | C77: Deposited | D77: PMT-S151-150272 | F77: USD | G77: -3300 | H77: -3300 | I77: 3300 | J77: -3300 | K77: Fishburne Military School | L77: Jose Castellanos | M77: CHECK
A78: 102 - US | B78: 46146 | C78: Deposited | D78: PMT-S151-223743 | F78: USD | G78: -3187.5 | H78: -3187.5 | I78: 3187.5 | J78: -3187.5 | K78: The Hanover Insurance Company
A79: 102 - US | B79: 44694 | C79: Deposited | D79: PMT-S151-147510 | E79: IN-S151-536994 | F79: USD | G79: -6000 | H79: -6000 | I79: 3000 | J79: -3000 | K79: High Bar Brands | L79: Stephanie Thore | M79: CHECK
A80: 102 - US | B80: 45084 | C80: Deposited | D80: PMT-S151-169389 | F80: USD | G80: -2979 | H80: -2979 | I80: 2979 | J80: -250567.82 | K80: DUMMY CUSTOMER_CASHAPPS 102 - US | M80: FOREIGN REMITTANCE CREDIT 33RECD CHIP DEUTSCHE BANK AG*ORG:EPPENDORF NEDERLAND B .V.,NETHERLANDS-NL,6546 BC NIJMEGE*OGB:DEUTSCHE BANK AG,AMSTERDAM,DE ENTREE 196*BNF:MELTWATER NEWS US INC,REDWOOD CITY CA/US,STE 165*OBI:2023-400 -003 05/01/23*STCHIPSEQ:0022320*TIME:0000*YOUR REF:SIP/02.06-10:52*OUR REF:15 8317944
A81: 102 - US | B81: 45883 | C81: Deposited | D81: PMT-S151-209465 | E81: IN-S151-584586 | F81: USD | G81: -36131.26 | H81: -36131.26 | I81: 2963.26 | J81: -2963.26 | K81: L.A. Care Health Plan | L81: Jose Castellanos | M81: ACH CONCENTRATION CREDIT ACH CASH CONCENTRATION L.A. CARE HEALTH-122000661
A82: 102 - US | B82: 45866 | C82: Deposited | D82: PMT-S151-208422 | F82: USD | G82: -2636.66 | H82: -2636.66 | I82: 2636.66 | J82: -2636.66 | K82: Survivors Network of those Abused by Priests (SNAP)
A83: 102 - US | B83: 45884 | C83: Deposited | D83: PMT-S151-209557 | F83: USD | G83: -2625 | H83: -2625 | I83: 2625 | J83: -2625 | K83: Green Check Verified | M83: ACH CONCENTRATION CREDIT ACH CASH CONCENTRATION GREEN CHECK VERI-MERCURYACH Green Che MercuryACH MRCR-QVA1TXX X5U
A84: 102 - US | B84: 44992 | C84: Deposited | D84: PMT-S151-164531 | F84: USD | G84: -2550 | H84: -2550 | I84: 2550 | J84: -250567.82 | K84: DUMMY CUSTOMER_CASHAPPS 102 - US | M84: ACH CONCENTRATION CREDIT ACH CORP TRADE PAYMENT FROM HOPE GAS,INC. HOPE GAS,PAYMENTS 188413095
A85: 102 - US | B85: 44733 | C85: Deposited | D85: PMT-S151-149275 | F85: USD | G85: -2425 | H85: -2425 | I85: 2425 | J85: -2425 | K85: Matrix LLC | M85: CHECK
A86: 102 - US | B86: 45933 | C86: Deposited | D86: PMT-S151-211737 | E86: IN-S151-586645 | F86: USD | G86: -2500 | H86: -2500 | I86: 2300 | J86: -2300 | K86: Thunder Tech | M86: ACH CONCENTRATION CREDIT ACH CASH CONCENTRATION THUNDERTECH-9.30.25 THUNDERTE 9.30.25 MELTWATER
A87: 102 - US | B87: 45209 | C87: Deposited | D87: PMT-S151-176048 | E87: IN-S151-560145 | F87: USD | G87: -6360.82 | H87: -6360.82 | I87: 2259.39 | J87: -2259.39 | K87: National Sorghum Producers | M87: CHECK
A88: 102 - US | B88: 45202 | C88: Deposited | D88: PMT-S151-175765 | F88: USD | G88: -2177.51 | H88: -2177.51 | I88: 2177.51 | J88: -2177.51 | K88: Insight Venture Management | L88: Jason Welch | M88: ACH CONCENTRATION CREDIT ACH CORP TRADE PAYMENT FROM INSIGHT VENTURE INSIGHT V DIRECT-PAY 53852876
A89: 102 - US | B89: 46098 | C89: Deposited | D89: PMT-S151-221300 | F89: USD | G89: -2150 | H89: -2150 | I89: 2150 | J89: -250567.82 | K89: DUMMY CUSTOMER_CASHAPPS 102 - US | M89: ACH CONCENTRATION CREDIT ACH CASH CONCENTRATION AMERICAN FOREIGN-BILL.COM American Bill.com 015MRNWKHRWP 41O
A90: 102 - US | B90: 44869 | C90: Deposited | D90: PMT-S151-157433 | F90: USD | G90: -2085 | H90: -2085 | I90: 2085 | J90: -250567.82 | K90: DUMMY CUSTOMER_CASHAPPS 102 - US | M90: ACH CONCENTRATION CREDIT ACH CASH CONCENTRATION UNITED NATIONS-3305888902 UNITED NA 3305888902 3305888902
A91: 102 - US | B91: 44848 | C91: Deposited | D91: PMT-S151-156027 | F91: USD | G91: -2032.49 | H91: -2032.49 | I91: 2032.49 | J91: -2032.49 | K91: Feeding Westchester | M91: CHECK
A92: 102 - US | B92: 45194 | C92: Deposited | D92: PMT-S151-175314 | E92: IN-S151-559407 | F92: USD | G92: -4000 | H92: -4000 | I92: 2000 | J92: -2000 | K92: BioSTL | M92: ACH CONCENTRATION CREDIT ACH CASH CONCENTRATION BIOGENFU1 3638-PAYMENTS BIOGENFU1 PAYMENTS Meltwater News
A93: 102 - US | B93: 45593 | C93: Deposited | D93: PMT-S151-195665 | E93: IN-S151-574748 | F93: USD | G93: -22000 | H93: -22000 | I93: 2000 | J93: -2000 | K93: Cover Genius Trading Pty Ltd | M93: COVER GENIUS HOLDINGS PTY LTD COUPA PAY 821-2622 COVER GENIUS HOL DINGS PTY LTD TMATE /ROC/12397127124613 FX USD 22000.00 AT 0.6756200 200226969/TMS/2024-10-27T21:33:18 GMT/MID/0.661282
A94: 102 - US | B94: 44872 | C94: Deposited | D94: PMT-S151-157478 | F94: USD | G94: -1800 | H94: -1800 | I94: 1800 | J94: -1800 | K94: Concord University | L94: Jose Castellanos-103 | M94: IN-S151-544931 got credited CM-S151-13155
A95: 102 - US | B95: 46003 | C95: Deposited | D95: PMT-S151-215552 | F95: USD | G95: -1750 | H95: -1750 | I95: 1750 | J95: -250567.82 | K95: DUMMY CUSTOMER_CASHAPPS 102 - US | M95: ACH CONCENTRATION CREDIT ACH CASH CONCENTRATION ELEVATED CULTIVA-E CULT ELEVATED E CULT E CULTIVATION
A96: 102 - US | B96: 44862 | C96: Deposited | D96: PMT-S151-157014 | F96: USD | G96: -1500 | H96: -1500 | I96: 1500 | J96: -250567.82 | K96: DUMMY CUSTOMER_CASHAPPS 102 - US | M96: ACH CONCENTRATION CREDIT ACH CORP TRADE PAYMENT FROM LAWRENCE LIV NAT LAWRENCE PAYABLES LAWRENCE LIVERM
A97: 102 - US | B97: 45960 | C97: Deposited | D97: PMT-S151-213059 | F97: USD | G97: -1500 | H97: -1500 | I97: 1500 | J97: -1500 | K97: Echelon Insights | L97: Yangzom Vitali-116 | M97: FOREIGN REMITTANCE CREDIT 33RECD CHIP PNC BANK*ORG:ECHELON INSIGHTS LLC,ALEX ANDRIA VA 22314 3029 US,STE 250*OGB:PNC BANK,N.A.,US/CAMP HILL,17001-0297,PA 500 FIRST AVEN*BNF:MELTWATER NEWS US INC,REDWOOD CITY CA/US,275 SHO* BBI:/INT/202510884077*STCHIPSEQ:00158840*TIME:0111*YOUR REF:IN-S151-587978*OU R REF:303170378
A98: 102 - US | B98: 46038 | C98: Deposited | D98: PMT-S151-217537 | F98: USD | G98: -1498.72 | H98: -1498.72 | I98: 1498.72 | J98: -1498.72 | K98: Elevate Textiles | M98: ACH CONCENTRATION CREDIT ACH CORP TRADE PAYMENT FROM ELEVATE TEXTILES ELEVATE T CORP PMT 488174
A99: 102 - US | B99: 46143 | C99: Deposited | D99: PMT-S151-223677 | F99: USD | G99: -1450 | H99: -1450 | I99: 1450 | J99: -1450 | K99: Celigo CAM USD
A100: 102 - US | B100: 45533 | C100: Deposited | D100: PMT-S151-192922 | F100: USD | G100: -1379.91 | H100: -1379.91 | I100: 1379.91 | J100: -250567.82 | K100: DUMMY CUSTOMER_CASHAPPS 102 - US | M100: ACH CONCENTRATION CREDIT ACH CASH CONCENTRATION DANIEL J EDELMAN-PAYMENTS Daniel J PAYMENTS 01VEND031547 USD
...

Sheet Sheet2
A1: 102 - US | B1: Americas
A2: 105 - Owler | B2: Americas
A3: 107 - Linkfluence Corp | B3: Americas
A4: 10C (106) - Sysomos US | B4: Sysomos
A5: 111 - Canada | B5: Americas
A6: 11C (116) - Meltwater News Canada 2 | B6: Sysomos
A7: 131 - Brazil | B7: Americas
A8: 201 - Australia | B8: APAC
A9: 211 - China | B9: APAC
A10: 221 - HK | B10: APAC
A11: 231 - Japan | B11: APAC
A12: 241 - Singapore | B12: APAC
... A33: 335 - Scoop.it SAS | B33: EMEA

Sheet AMERICAS APRIL 2026
A1: Date | B1: Amount Remaining | C1: Number | D1: Customer Name | E1: AR Specialist | F1: Memo
A2: 46118 | B2: 20913.77 | C2: PMT-S151-222326 | D2: Camp Chef | F2: ACH CONCENTRATION CREDIT ACH CASH CONCENTRATION BUSHNELL OPER-PAYMENT BUSHNELL PAYMENT 2021416
A3: 46127 | B3: 20698 | C3: PMT-S151-222780 | D3: Culloton + Bauer Luce | F3: ACH CONCENTRATION CREDIT ACH CASH CONCENTRATION CULLOTON STRATEG-ACH PAYMEN Culloton ACH Paymen 95267
A4: 46139 | B4: 19350 | C4: PMT-S151-223322 | D4: Gaudenzia, Inc
A5: 46132 | B5: 17200 | C5: PMT-S151-223019 | D5: Gordon State College | F5: ACH CONCENTRATION CREDIT ACH CORP TRADE PAYMENT FROM Gordon State Col Gordon St CTX 0000039074
A6: 46139 | B6: 15000 | C6: PMT-S151-223397 | D6: Nautilus Solar Energy, LLC | F6: ACH CONCENTRATION CREDIT ACH CASH CONCENTRATION NAUTILUS SOLAR E-ACH PMT NAUTILUS ACH Pmt 11216430243
A7: 46136 | B7: 9900 | C7: PMT-S151-223327 | D7: DUMMY CUSTOMER_CASHAPPS 102 - US | F7: ACH CONCENTRATION CREDIT ACH CASH CONCENTRATION COMMISSION L'UNI-PAYMENT COMMISSIO PAYMENT KQ3LUSEQGD69
A8: 46126 | B8: 7500 | C8: PMT-S151-222677 | D8: DUMMY CUSTOMER_CASHAPPS 102 - US
A9: 46136 | B9: 6200 | C9: PMT-S151-223212 | D9: Honolulu Marathon Association | E9: Stephanie Thore
A10: 46135 | B10: 4265.16 | C10: PMT-S151-223214 | D10: TFI Family Services, Inc. | F10: ACH CONCENTRATION CREDIT ACH CASH CONCENTRATION TFI FAMILY SERVI-ACH PAYMEN TFI Famil ACH Paymen V000000551
A11: 46113 | B11: 10 | C11: PMT-S151-222271 | D11: The Stronach Group | F11: ACH CONCENTRATION CREDIT ACH CASH CONCENTRATION 1/ST LLC-PAYMENTJNL 1/ST LLC PAYMENTJNL MELTW-CORP
A12: 46140 | B12: 49625.782 | C12: PMT-S130-48216 | D12: DUMMY CUSTOMER_CASHAPPS 111 - Canada | F12: ACH: THE CURRENCY CL THE CURRENCY CLOUD LIMITED RE:Meltwater News Canada Inc
A13: 46120 | B13: 2104.691 | C13: PMT-S130-48077 | D13: Weber Shandwick | E13: Frida Emri | F13: ACH: Weber Shandwick WEBER SHANDWICK CAN RE:MELTWATER NEWS CANADA INC
A14: 46113 | B14: 220.631 | C14: PMT-S130-48041 | D14: Wellington Altus Private Wealth | F14: ACH: WELLINGTONALTUS WELLINGTONALTUSPRIVATEWEALTH RE:MELTWATER NEWS CANADA INC

Sheet APAC APRIL 2026
A1: Date | B1: Amount Remaining | C1: Number | D1: Customer Name | E1: AR Specialist | F1: Memo
A2: 46121 | B2: 13203.96 | C2: PMT-S155-42950 | D2: DUMMY CUSTOMER_CASHAPPS 201 - Australia | E2: Windy Go | F2: 173200023166926 MARS NEDERLAND B 0001975
A3: 46133 | B3: 11789.25 | C3: PMT-S155-43051 | D3: DUMMY CUSTOMER_CASHAPPS 201 - Australia | E3: Windy Go | F3: Meltwater Pont3 Pty Limite 0599873
A4: 46136 | B4: 529.445 | C4: PMT-S155-43101 | D4: DUMMY CUSTOMER_CASHAPPS 201 - Australia | E4: Windy Go | F4: 689647123400424153 VERVESUPER 0780254
A5: 46132 | B5: 201.025 | C5: PMT-S155-43042 | D5: DUMMY CUSTOMER_CASHAPPS 201 - Australia | E5: Windy Go | F5: CVENTPAYMENTS-DMRH CVENTPAYMENTS 0530766
A6: 46139 | B6: 134.84 | C6: PMT-S155-43111 | D6: DUMMY CUSTOMER_CASHAPPS 201 - Australia | E6: Windy Go | F6: CVENTPAYMENTS-HRNO CVENTPAYMENTS 0832990
A7: 46127 | B7: 3822.059 | C7: PMT-S158-12595 | D7: Suyen Corporation | F7: Payment for 241-Singapore IN-S158-410328 received in 221-HK
A8: 46127 | B8: 3351.286 | C8: PMT-S158-12593 | D8: SM PRIME HOLDINGS INC. | F8: 1/SM PRIME HOLDINGS INC IN S158 410331 SOCIAL MEDIA CRISIS MANAGEMENT SUBSCRIPTION FX USD 32076.80 AT 1.2459590 528325969 /TMS/2026-04-15T08:14:19 GMT/MID/1.271462
A9: 46142 | B9: 1498.977 | C9: PMT-S158-12708 | D9: St. Luke's Medical Center | F9: ST LUKE S MEDICAL CENTER GLOBAL CIT IN S158 410605 CA ADDITIONAL SEARCH ES USERS AND SITE REVIEWS FX USD 14235.50 AT 1.2544360 529153071 /TMS/2026-04-30T01:17:09 GMT/MID/1.280822
A10: 46128 | B10: 777.741 | C10: PMT-S158-12609 | D10: Intelligent Beauty Skin Solutions, Inc. Business Style: Belo Medical Group | F10: INTELLIGENT BEAUTY SKIN SOLUTIONS I IN S158 410316 HO FX USD 7433.00 AT 1.2453140 528384503/TMS/2026-04-16T07:40:19 GMT/MID/1.270803
A11: 46140 | B11: 535.863 | C11: PMT-S158-12678 | D11: LouderPH | F11: 1/LOUDERPH INC /URI/OTHER-PAYMENT OF MONTHLY SUBSC RIPTI 6562385010///ROC/PHNTR0225355 /1 FX USD 5115.60 AT 1.2492210 529004653/TMS/2026-04-28T01:17:03 GMT/MID/1.274802

Sheet EMEA APRIL 2026
A1: Date | B1: Amount Remaining | C1: Number | D1: Customer Name | E1: AR Specialist | F1: Memo
A2: 46128 | B2: 5330.002 | C2: PMT-S109-55181 | D2: VDI Technologiezentrum GmbH | E2: Theresa Saal | F2: 0402641043 1480429017260416 /ORD.CUST/VDI TECHNOLOGIEZENTRUM GMBH/EREF/0402641043/PAY.DET./IN S109-449170+
A3: 46134 | B3: 4174.937 | C3: PMT-S109-55252 | D3: Newspress Spain SL | E3: Nathalie Darmois | F3: NONREF 1480524653260422 /ORD.CUST/NEWSPRESS SPAIN,S.L./PAY.DET./IN-S109-449013
A4: 46135 | B4: 3526.851 | C4: PMT-S109-55263 | D4: Stadtkrankenhaus Delmenhorst GmbH | E4: Theresa Saal | F4: NONREF DE26042392928652 /ORD.CUST/DERDENGELDEN CMC WORLDWI/PAY.DET./IN-S109-448037/352110
A5: 46134 | B5: 3157.515 | C5: PMT-S109-55250 | D5: QUOBLY | E5: Nathalie Darmois | F5: MELTWATER.IN-S10 1480524438260 422 /ORD.CUST/QUOBLY/EREF/MELTWATER.IN-S109-449006.0/PAY.DET./IN-S109 449006
A6: 46120 | B6: 1281.249 | C6: PMT-S109-55090 | D6: CONSEIL SUPERIEUR DU NOTARIAT | E6: Nathalie Darmois | F6: 20260403.D55.253 14802425242604 08 /ORD.CUST/CONSEIL SUPERIEUR DU NOTARIAT/EREF/20260403.D55.253.8/P AY.DET./A
A7: 46139 | B7: 809.552 | C7: PMT-S109-55285 | D7: Landesdirektion Sachsen | E7: Theresa Saal | F7: 8300397767 1480612737260427 /ORD.CUST/HAUPTKASSE DES FREISTAATES SACHSEN/EREF/8300397767/PAY. DET./RNR.IN-S109-449247 RD.01.04.2026 SO CIAL MEDIA M .. TORING 04/2026 MEHRJAHRESVERTRAG HTTP.//
A8: 46141 | B8: 262.857 | C8: PMT-S109-55316 | D8: Urban Technology GmbH | E8: Theresa Saal | F8: NONREF DE26042993041090 /ORD.CUST/URBAN TECHNOLOGY GMBH/PAY.DET./IN-S109-445806 PAYMENT P LAN
A9: 46142 | B9: 7152.393 | C9: PMT-S104-51044 | D9: AFRODAD (African Forum & Network on Debt Development) | E9: Georgia Albutt-392 | F9: /REMI//URI/AFRODAD MELTWATER IN- S104-435161///ROC/OT26117ZW014101 7 S06611922E2601 /INS/SBZAZAJJ/OCMT/USD7290,00//BENM/GB84HBUK4011 6031212125 Meltwater (UK) Limited/EXCH/1.3762573//ORDP/AFRODAD 91 40000882177 31 ATKINSON DRIVE HILLSIDE/OBK/SBICZWHXXXX STANBIC BA NK ZIMBABWE LIMITED OTTOMAN HOUSE 59 SAMORA MACHEL AVENUE H/TMS/2 026-04-30T05:12:48 GMT/MID/1.34655650
A10: 46114 | B10: 1382.376 | C10: PMT-S104-50722 | D10: DUMMY CUSTOMER_CASHAPPS 321 - UK | E10: Amy Tyler | F10: /REMI/BEING PAYMENT FOR 2026 HOO TSUITE SUBSCRIPTION S0660923A0EF0 1/OCMT/USD1385,00//BENM/GB84HBUK40116031212125 Meltwater (UK) Lim ited/EXCH/1.3528468//ORDP/ECOBANK ZAMBIA LTD 154000204 22768 ACAC IA PARK THABO MBEKI ROAD P.O. B/OBK/ECOCZMLUXXX ECOBANK ZAMBIA LI MITED THABO MBEKI ROAD LUSAKA/TMS/2026-04-02T16:16:10 GMT/MID/1.3 2365590
A11: 46120 | B11: 675.14 | C11: PMT-S104-50747 | D11: MND Scotland | E11: Amy Tyler | F11: MND Scotland FP637B1734888997 /DbAcct/80071500767080 /ROC/S104-440219 /FPID/3000000017492138091020260408826800715
A12: 46135 | B12: 5551.375 | C12: PMT-S114-7017 | D12: Mood Design Trading Company (Single Person LLC) | F12: M0D FOR DESING AND COOOERCIAL COMPA /REF/OPERATIONAL EXPENSES PAYMENT O F INVOICE408110MOOD
A13: 46141 | B13: 4584.865 | C13: PMT-S114-7034 | D13: Fann Atheer LilDhi'ayah wal-I'lan (INVENU) | E13: Manar Sultan | F13: 1/INVENU COMPANY LAST PAYMENT FOR MELTWATER SETTLEME NT OF BILL FX USD 30956.00 AT 3.6530000 219244593 /TMS/2026-04-29T04:17:27 GMT/MID/3.6731200
A14: 46127 | B14: 368.035 | C14: PMT-S114-6999 | D14: Alizz Islamic Bank SAOC | E14: Manar Sultan | F14: ALIZZ ISLAMIC BANK VENDOR PAYMENT IN-S114-408098 FX USD 3700.00 AT 3.6530000 218592617/TMS/2026-04-15T12:18:30 GMT/MID/3.6731200
A15: 46128 | B15: 407.657 | C15: PMT-S144-11906 | D15: DUMMY CUSTOMER_CASHAPPS 391 - South Africa | E15: Jan Sutherland | F15: PAYMASTER PEOPLE SOLUTIONS PTY
A16: 46136 | B16: 5154.702 | C16: PMT-S117-13150 | D16: DUMMY CUSTOMER_CASHAPPS 401 - India | E16: Prabhat Aggarwal | F16: /00060330006652 LOTTEINDIACORPORATIONPRIVATELTD 2026/04/24 183004 HDFC042450066005 HDFCR52026042450066005
A17: 46122 | B17: 13008.558 | C17: PMT-S146-28090 | D17: Aktiebolaget Stockholms Spårvägar | E17: Max Hugo Larsson Ras Vidal | F17: STOCKHOLMS SPÅRVÄGAR AB
A18: 46134 | B18: 3692.742 | C18: PMT-S127-14174 | D18: Epax Norway AS | E18: Katarina Andersson | F18: 6535 079740586535 34500.00 34500.00 IBS 34500.00 EPAX NORWAY AS 5805 NO POSTBOKS 444 5805 BERGEN 15039928652 BBAN Meltwater News AS 0158 NO Nedre Vollgate 3 0158 OSLO 50100542177 BBAN CINV IN -S127-414250 34500.00 2026-04-22T00:00:00+02:00 2026-04-22 1 Overføring innland E86535
A19: 46142 | B19: 2781.598 | C19: PMT-S127-14184 | D19: EB MARINE AS | E19: Katarina Andersson | F19: 613 25987.50 EB MARINE AS MIDTG$RDVEIEN 16 4031 60750573188 BBAN 50100542177 BBAN EB MARINE AS 2026-04-30 2 Overføring innland 66761127059
